Workbook

Sheet Read Me
B2: Product Manager Onboarding · Phase 1: Foundations
B5: At a glance
B6: Totals | C6: 225 hrs · 9 modules · 76 tasks · basics to advanced
B7: Track | C7: Discovery and product thinking + Delivery + Working fluently with Claude (Chat, Cowork, Design)
B8: Audience | C8: New product manager, joining directly after graduation
B9: Tooling | C9: Claude Chat, Claude Cowork, Claude Design. No Figma.
B10: Practice material | C10: Three fictional client briefs, included in Appendix A
B12: The sheets in this workbook
B13: Read Me | C13: This sheet. The framing from the plan, carried over word for word.
B14: Dashboard | C14: Live progress. Every figure is a formula — nothing on it is typed by hand.
B15: Task Tracker | C15: All 76 tasks, grouped under a banner row for each module carrying that module's goal, introduction and checkpoint list. Each task is one merged block; its exercise steps are the rows inside it. You tick off steps — task status and task hours fill in on their own.
B16: Practice Briefs | C16: The three fictional client briefs in full, with what each deliberately leaves out.
B17: Prompt Library | C17: The twelve starter prompts. Add your own beneath them.
B18: Journal | C18: Your daily log. Fifteen minutes at the end of each day.
B19: Phase 2 Readiness | C19: The 29-point checklist. Fill this in once, at Task 8.10.
B21: What you fill in
B22: Task Tracker | C22: Step status, Start, End and Hrs — one set per exercise step. Task status and task hours are formulas and fill in by themselves.
B23: Prompt Library | C23: Your own notes, and your own prompts beneath the starters.
B24: Journal | C24: Every day. Phase 2 Readiness: once, at the end.
B25: Everything else | C25: Content from the plan, or a formula. You should not need to edit it.
B27: A note on hours
C28: The hour figures are estimates to help you pace yourself, not targets to hit. Logging more than the estimate on a task is information, not a problem.
B30: A note to you, before you begin
C31: Welcome. You are about to spend a few focused weeks learning three things at once: how to work out what's worth building, how to get it built, and how to work alongside Claude. That last one is not a bonus skill here — it is how we work every day. By the end of this phase, reaching for Claude should feel as natural to you as opening a browser tab.
C32: This plan is deliberately unhurried. Take the time each topic needs — depth is what we're after, and there's no advantage in rushing past something before it has clicked. What matters is that at the end you can look at a vague client request, a delivery team and a deadline, and know exactly what to do next.
C33: A few things to know about how this is built:
B34: Every task stands alone | C34: Each one tells you what to do, what to read or watch, what to produce, and roughly how long it should take. You can stop mid-module and pick up cleanly the next day.
B35: Most tasks end with something you made | C35: A document, a critique, a spec, a screen, a roadmap. Reading alone doesn't build skill. By the end of Phase 1 you will have a folder of roughly sixty artefacts — that folder is your portfolio and your proof.
B36: Claude is your study partner, not your answer machine | C36: In many tasks you will be asked to explain a concept *to* Claude and have it find the holes in your understanding. That feels backwards at first. Stick with it — it is the fastest way to find out what you only *think* you understand.
B37: You'll build some things twice, on purpose | C37: A few tasks ask you to make a rough first version and then improve it. Seeing the difference between the two is where the learning lives.
B38: You are not training to be a designer | C38: You will prototype, critique screens and read front-end code — but always to sharpen a requirement or a conversation, never to own the craft. Module 3 is deliberately short for exactly this reason.
B39: Ask early | C39: If you're stuck for more than thirty minutes on something that isn't meant to be hard, reach out to your mentor. Asking is always welcome here, and it's usually the fastest route forward.
B41: How the phase is paced
B42: Rhythm | C42: Roughly six weeks at full time. Modules 0–2 are your first fortnight, Modules 3–4 build the bridge to design and engineering, Module 5 is the operational core, and Modules 6–8 pull everything together.
B43: One standing habit | C43: Fifteen minutes at the end of every day in your learning journal (set up in Task 0.3). Three lines: what I made, what confused me, what I want to ask. It's the one habit that runs right through the plan, and it's worth protecting.
B44: A note on links | C44: Every URL here was working when this plan was written. If one has moved, search the title rather than giving up — and tell your mentor so it can be fixed for the next person.
B46: Footer | C46: Phase 1 · Product Manager Onboarding · 225 hrs · 9 modules · 76 tasks · Practice briefs: PawPal, Harvest Hub, ClaimLens · Phase 2 (Claude Code, repositories, working in project repos, live project work) to follow

Sheet Dashboard
B2: Phase 1 — Progress
B3: Everything on this sheet is a formula. Update the Task Tracker and these figures follow.
B5: Overall
B6: Measure | C6: Complete | D6: Total | E6: % complete
B7: Tasks complete | C7: =COUNTIF('Task Tracker'!$F:$F,"Done") | D7: =COUNT('Task Tracker'!$E:$E) | E7: =IFERROR(C7/D7,0)
B8: Hours complete | C8: =SUMIF('Task Tracker'!$F:$F,"Done",'Task Tracker'!$E:$E) | D8: =SUM('Task Tracker'!$E:$E) | E8: =IFERROR(C8/D8,0)
B9: Modules fully complete | C9: =SUMPRODUCT(--(C25:C33=D25:D33)) | D9: 9 | E9: =IFERROR(C9/D9,0)
B11: Effort and status
B12: Hours logged so far (sum of step hours) | C12: =SUM('Task Tracker'!$M:$M)
B13: Hours estimated for tasks with time logged | C13: =SUMIF('Task Tracker'!$G:$G,">0",'Task Tracker'!$E:$E)
B14: Difference (logged − estimated) | C14: =C12-C13
B15: Tasks in progress | C15: =COUNTIF('Task Tracker'!$F:$F,"In progress")
B16: Tasks blocked | C16: =COUNTIF('Task Tracker'!$F:$F,"Blocked")
B17: Tasks not started | C17: =COUNTIF('Task Tracker'!$F:$F,"Not started")
B19: Where you are now
B20: Current task | C20: {=IFERROR(INDEX('Task Tracker'!$A:$A,MATCH("In progress",'Task Tracker'!$F:$F,0)),IFERROR(INDEX('Task Tracker'!$A:$A,MATCH("Not started",'Task Tracker'!$F:$F,0)),"All complete"))}
B21: Title | C21: {=IFERROR(INDEX('Task Tracker'!$C:$C,MATCH($C$20,'Task Tracker'!$A:$A,0)),"")}
B23: By module
B24: Module | C24: Tasks done | D24: Tasks | E24: % tasks | F24: Hours done | G24: Hours | H24: % hours
B25: 0 · Landing Well | C25: =COUNTIFS('Task Tracker'!$B:$B,0,'Task Tracker'!$F:$F,"Done") | D25: 6 | E25: =IFERROR(C25/D25,0) | F25: =SUMIFS('Task Tracker'!$E:$E,'Task Tracker'!$B:$B,0,'Task Tracker'!$F:$F,"Done") | G25: 16 | H25: =IFERROR(F25/G25,0)
B26: 1 · Claude Foundations | C26: =COUNTIFS('Task Tracker'!$B:$B,1,'Task Tracker'!$F:$F,"Done") | D26: 9 | E26: =IFERROR(C26/D26,0) | F26: =SUMIFS('Task Tracker'!$E:$E,'Task Tracker'!$B:$B,1,'Task Tracker'!$F:$F,"Done") | G26: 22 | H26: =IFERROR(F26/G26,0)
B27: 2 · Discovery and Problem Definition | C27: =COUNTIFS('Task Tracker'!$B:$B,2,'Task Tracker'!$F:$F,"Done") | D27: 7 | E27: =IFERROR(C27/D27,0) | F27: =SUMIFS('Task Tracker'!$E:$E,'Task Tracker'!$B:$B,2,'Task Tracker'!$F:$F,"Done") | G27: 20 | H27: =IFERROR(F27/G27,0)
B28: 3 · Working with Designers | C28: =COUNTIFS('Task Tracker'!$B:$B,3,'Task Tracker'!$F:$F,"Done") | D28: 3 | E28: =IFERROR(C28/D28,0) | F28: =SUMIFS('Task Tracker'!$E:$E,'Task Tracker'!$B:$B,3,'Task Tracker'!$F:$F,"Done") | G28: 8 | H28: =IFERROR(F28/G28,0)
B29: 4 · From Idea to Screen | C29: =COUNTIFS('Task Tracker'!$B:$B,4,'Task Tracker'!$F:$F,"Done") | D29: 10 | E29: =IFERROR(C29/D29,0) | F29: =SUMIFS('Task Tracker'!$E:$E,'Task Tracker'!$B:$B,4,'Task Tracker'!$F:$F,"Done") | G29: 31 | H29: =IFERROR(F29/G29,0)
B30: 5 · Delivery | C30: =COUNTIFS('Task Tracker'!$B:$B,5,'Task Tracker'!$F:$F,"Done") | D30: 13 | E30: =IFERROR(C30/D30,0) | F30: =SUMIFS('Task Tracker'!$E:$E,'Task Tracker'!$B:$B,5,'Task Tracker'!$F:$F,"Done") | G30: 40 | H30: =IFERROR(F30/G30,0)
B31: 6 · Product Sense and AI Patterns | C31: =COUNTIFS('Task Tracker'!$B:$B,6,'Task Tracker'!$F:$F,"Done") | D31: 10 | E31: =IFERROR(C31/D31,0) | F31: =SUMIFS('Task Tracker'!$E:$E,'Task Tracker'!$B:$B,6,'Task Tracker'!$F:$F,"Done") | G31: 32 | H31: =IFERROR(F31/G31,0)
B32: 7 · Cowork and Scaling Yourself | C32: =COUNTIFS('Task Tracker'!$B:$B,7,'Task Tracker'!$F:$F,"Done") | D32: 8 | E32: =IFERROR(C32/D32,0) | F32: =SUMIFS('Task Tracker'!$E:$E,'Task Tracker'!$B:$B,7,'Task Tracker'!$F:$F,"Done") | G32: 23 | H32: =IFERROR(F32/G32,0)
B33: 8 · Capstone — Brief to Prototype | C33: =COUNTIFS('Task Tracker'!$B:$B,8,'Task Tracker'!$F:$F,"Done") | D33: 10 | E33: =IFERROR(C33/D33,0) | F33: =SUMIFS('Task Tracker'!$E:$E,'Task Tracker'!$B:$B,8,'Task Tracker'!$F:$F,"Done") | G33: 33 | H33: =IFERROR(F33/G33,0)
B34: TOTAL | C34: =SUM(C25:C33) | D34: =SUM(D25:D33) | E34: =IFERROR(C34/D34,0) | F34: =SUM(F25:F33) | G34: =SUM(G25:G33) | H34: =IFERROR(F34/G34,0)

Sheet Task Tracker
A1: Task ID | B1: Module | C1: Task | D1: Type | E1: Est. hrs | F1: Task status (auto) | G1: Task hrs (auto) | H1: Step | I1: Exercise step | J1: Step status | K1: Start | L1: End | M1: Hrs | N1: Why it matters | O1: Resources | P1: Note for you | Q1: Builds on | R1: Confidence 1-5 | S1: Comments
A2: Module 0 · Landing Well — 16 hrs · 6 tasks
A3: Goal | C3: I know how this place works, my tools are set up, and I know how to conduct myself.
A4: About | C4: Before any product work, a short module about the ground you're standing on. You've come straight from university, where the rules were mostly written down. At work they usually aren't. These six tasks make the unwritten parts explicit so you're not guessing. ---
A5: Checkpoint | C5: Bring to your mentor: your five policy situations written out, your journal set up with three entries, your before-and-after transparency messages, your dark-pattern redesign, and your blocker template. ---
A6: 0.1 | B6: 0 | C6: Read: Company policies — mandatory | D6: Read | E6: 6 | F6: =IF(COUNTIF($J6:$J11,"Done")=6,"Done",IF(COUNTIF($J6:$J11,"Blocked")>0,"Blocked",IF(COUNTIF($J6:$J11,"To do")=6,"Not started","In progress"))) | G6: =IF(SUM($M6:$M11)=0,"",SUM($M6:$M11)) | H6: 1 | I6: Read every policy document end to end, once, without taking notes. | J6: Done | K6: 46031 | L6: 46090 | M6: 15 | N6: Every new joiner reads and formally acknowledges our policies before touching project work. This is the one task in the plan that is genuinely compulsory. Budget a full working day for it. There's a good amount of material, and it rewards proper reading rather than a quick pass. | O6: • Our policy set — *HR or your mentor will share these with you* | P6: Step 4 is the real point of this task. Policies are easy to read and hard to apply — knowing in advance what you'd do in those five situations is what stops you improvising badly under pressure. You'll revisit the AI-and-client-data part properly in Task 7.5. --- --- | Q6: — | R6: 5 | S6: a client asks you to share another client's work: Would respectfully deny it as it is a clear of breach of privacy. you want to put client work in your portfolio: Would avoid the personal details of the client and the numbers related to the business or any other information which is restricted. you're working from a café on public wifi: The first thing is to ask myself that why am I doing this? Then I would switch to my personal wi-fi or would turn on the company's VPN before accesing and work files. you need leave at short notice: Will inform the HR first, in person or on call. Then will fill the leave application form. someone outside the company asks what you're building: Will refuse to give the specifics about the features and tell them to contact the company's PR Team.
H7: 2 | I7: Read them a second time and write down everything you didn't understand, anything that surprised you, and any term, threshold or approval step you couldn't explain to someone else. | J7: Done | K7: 46272 | L7: 46273 | M7: 5
H8: 3 | I8: Check with your mentor before putting any internal document into an AI tool. Where you're cleared to, ask Claude to explain unfamiliar terms in plain language; where you're not, ask your mentor directly. | J8: Done | K8: 46273 | L8: 46273 | M8: 0.5
H9: 4 | I9: Write down what you would actually do in five specific situations: a client asks you to share another client's work; you want to put client work in your portfolio; you're working from a café on public wifi; you need leave at short notice; someone outside the company asks what you're building. | J9: Done | K9: 46273 | L9: 46273 | M9: 0.25
H10: 5 | I10: Take your open questions to your mentor, then complete whatever acknowledgement or sign-off we require. | J10: Done | K10: 46273 | L10: 46273 | M10: -
H11: 6 | I11: Split this across two sittings if you'd like to. Policy documents are dense, and you'll get much more from the second half with fresh attention. | J11: Done | K11: 46272 | L11: 46273 | M11: -
A12: 0.2 | B12: 0 | C12: Set up: Your tools and workspace | D12: Set up | E12: 1 | F12: =IF(COUNTIF($J12:$J16,"Done")=5,"Done",IF(COUNTIF($J12:$J16,"Blocked")>0,"Blocked",IF(COUNTIF($J12:$J16,"To do")=5,"Not started","In progress"))) | G12: =IF(SUM($M12:$M16)=0,"",SUM($M12:$M16)) | H12: 1 | I12: Log in to Claude and confirm your plan gives you Projects and file uploads. | J12: Done | K12: 46273 | L12: 46273 | M12: 0.05 | N12: Get your accounts, permissions and file structure sorted in one sitting so you never lose time to setup again. | O12: • Claude Help Center: https://support.claude.com • Claude Academy: https://academy.claude.com | P12: A small task with a long payoff. A properly set-up workspace saves you a little friction every single day for the next seven weeks. --- --- | Q12: — | R12: 5 | S12: Currently I have access to Cowork, Claude Design but not Jira and other internal skills.
H13: 2 | I13: Go to Settings → Capabilities and switch on code execution / file creation (Skills and file outputs depend on it). | J13: Done | K13: 46273 | L13: 46273 | M13: -
H14: 3 | I14: Create a folder structure on your machine: `01-Journal`, `02-Module-Work`, `03-Briefs`, `04-Prototypes`, `05-Reference-Library`. | J14: Done | K14: 46273 | L14: 46273 | M14: 0.15
H15: 4 | I15: Confirm with your mentor which internal tools you have access to today and which arrive later (Cowork, Claude Design, Jira, our internal Skills). | J15: Done | K15: 46273 | L15: 46273 | M15: 0.05
H16: 5 | I16: Bookmark: the Claude Help Center, Claude Academy, and this plan. | J16: Done | K16: 46273 | L16: 46273 | M16: 0.05
A17: 0.3 | B17: 0 | C17: Build: Your learning journal | D17: Build | E17: 2 | F17: =IF(COUNTIF($J17:$J21,"Done")=5,"Done",IF(COUNTIF($J17:$J21,"Blocked")>0,"Blocked",IF(COUNTIF($J17:$J21,"To do")=5,"Not started","In progress"))) | G17: =IF(SUM($M17:$M21)=0,"",SUM($M17:$M21)) | H17: 1 | I17: Create a Claude Project called *Phase 1 Learning Journal*. | J17: Done | K17: 46273 | L17: 46273 | M17: 0.1 | N17: Set up the one thing that runs through all ten modules — a daily record of what you made, what confused you, and what you want to ask. | O17: • Journal template: Appendix C of this plan • Claude Help Center — search "Projects": https://support.claude.com | P17: Fifteen minutes a day. In week seven you will reread week one and see exactly how far you've come — that evidence is worth more than you'd expect on a hard day. --- --- | Q17: — | R17: 5 | S17: After reading Claude's reply, I realized what I had missed and it was fun to read Claude's scolding. Claude's reply: "Looking at the Aug 9 entry: you said you were asked to turn on code execution/file creation under Settings > Capabilities but couldn't find it there. Did you check whether that toggle lives in your personal account settings at all, or whether it's actually an org-level admin control — something only your account's owner/admin can flip, not an individual user? If you didn't check that distinction, how would you find out who actually has that permission on your account before assuming the feature just doesn't exist?"
H18: 2 | I18: In the Project's custom instructions, paste something like: *"I'm a junior product manager in my first job, working through a structured onboarding plan. When I share a journal entry, ask me one sharp question about the thing I said confused me. Don't reassure me — help me find the gap."* | J18: Done | K18: 46273 | L18: 46273 | M18: 0.1
H19: 3 | I19: Copy the journal template from Appendix C into your `01-Journal` folder. | J19: Done | K19: 46273 | L19: 46273 | M19: -
H20: 4 | I20: Write today's entry now, covering Tasks 0.1 and 0.2. | J20: Done | K20: 46273 | L20: 46273 | M20: 0.25
H21: 5 | I21: Paste it into the Project and see what question Claude asks back. | J21: Done | K21: 46273 | L21: 46273 | M21: 0.5
A22: 0.4 | B22: 0 | C22: Learn: Transparency at work | D22: Learn | E22: 2 | F22: =IF(COUNTIF($J22:$J26,"Done")=5,"Done",IF(COUNTIF($J22:$J26,"Blocked")>0,"Blocked",IF(COUNTIF($J22:$J26,"To do")=5,"Not started","In progress"))) | G22: =IF(SUM($M22:$M26)=0,"",SUM($M22:$M26)) | H22: 1 | I22: Read the article. | J22: Done | K22: 46273 | L22: 46273 | M22: 0.5 | N22: Transparency is the difference between a project that recovers from a problem and one that doesn't. Understand what it actually means in practice — and where its limits are. | O22: • Indeed: *Being Transparent at Work* — https://www.indeed.com/career-advice/career-development/being-transparent | P22: The pattern to internalise: the earlier you share something, the more options everyone has. Flagging a deadline risk four days out is genuinely appreciated — it gives the team room to help, and it's exactly what a good colleague does. --- --- | Q22: — | R22: 5 | S22: 3 situations where speaking up would take courage: when you notice a flaw made by a senior executive, when you make a mistake and are afraid of dealing with the consequences, when you do the major work but struggle to stand up for yourself and hence let someone else take the credit of your work.
H23: 2 | I23: Write down three specific work situations where speaking up would take some courage — for example, realising on a Thursday that a Friday deadline is going to slip. | J23: Done | K23: 46273 | L23: 46273 | M23: 1
H24: 3 | I24: For each, draft the exact message you'd send. Real words, not a summary. | J24: Done | K24: 46273 | L24: 46273 | M24: 0.5
H25: 4 | I25: Ask Claude: *"Here are three messages a junior product manager might send in situations that take some courage. For each, tell me how it would land with a manager, and rewrite it to be equally honest but more useful."* | J25: Done | K25: 46273 | L25: 46273 | M25: 0.5
H26: 5 | I26: Save the before-and-after pairs in your journal. | J26: Done | K26: 46273 | L26: 46273 | M26: 0.1
A27: 0.5 | B27: 0 | C27: Learn: Ethics in work and in product | D27: Learn | E27: 3 | F27: =IF(COUNTIF($J27:$J31,"Done")=5,"Done",IF(COUNTIF($J27:$J31,"Blocked")>0,"Blocked",IF(COUNTIF($J27:$J31,"To do")=5,"Not started","In progress"))) | G27: =IF(SUM($M27:$M31)=0,"",SUM($M27:$M31)) | H27: 1 | I27: Read all four articles, then browse the deceptive design pattern types. | J27: Done | K27: 46274 | L27: 46274 | M27: 1.5 | N27: As a product manager you decide what gets built, which shapes what thousands of people do. Some of those choices are persuasive; some are manipulative. Learn to tell the difference before you have to make one under deadline pressure. | O27: • Indeed: *Examples of Ethics* — https://www.indeed.com/career-advice/career-development/example-of-ethics • HBR: *How to Manipulate Customers... Ethically* — https://hbr.org/2021/10/how-to-manipulate-customers-ethically • HBR: *How to Be a Leader Who Stays True to Their Ethics* — https://hbr.org/2021/09/how-to-be-a-leader-who-stays-true-to-their-ethics-2 • Planisware: *Project Management Ethics* — https://www.planisware.com/hub/blog/project-management-ethics-essential-ingredient-project-leadership • Deceptive Design pattern library — https://www.deceptive.design/types | P27: You will one day be asked to design something that makes cancelling hard. Knowing in advance what you'd say in that moment is the whole point of this task. --- --- | Q27: — | S27: https://docs.google.com/document/d/1Dd713Nui2pXCk6HDFUPmVUjzb743Jvp7Vik2MCzL56Y/edit?usp=sharing
H28: 2 | I28: Pick three dark patterns you've personally encountered in an app you use, and screenshot or describe them. | J28: Done | K28: 46274 | L28: 46274 | M28: 0.25
H29: 3 | I29: For each, write two sentences: what business goal it serves, and what it costs the user. | J29: Done | K29: 46274 | L29: 46274 | M29: 0.5
H30: 4 | I30: Redesign one of them — describe in words how you'd achieve the same business goal honestly. | J30: Done | K30: 46274 | L30: 46274 | M30: 0.15
H31: 5 | I31: Debate it with Claude: *"Argue the strongest case that this pattern is acceptable business practice. Then argue the strongest case against. Don't tell me which side you're on."* Note which argument you found harder to counter. | J31: Done | K31: 46274 | L31: 46274 | M31: 0.5
A32: 0.6 | B32: 0 | C32: Practise: How to ask a good question | D32: Practise | E32: 2 | F32: =IF(COUNTIF($J32:$J36,"Done")=5,"Done",IF(COUNTIF($J32:$J36,"Blocked")>0,"Blocked",IF(COUNTIF($J32:$J36,"To do")=5,"Not started","In progress"))) | G32: =IF(SUM($M32:$M36)=0,"",SUM($M32:$M36)) | H32: 1 | I32: Read both, focusing on the XY problem — asking about your attempted solution instead of your actual problem. | J32: Done | K32: 46274 | L32: 46274 | M32: 0.25 | N32: The single highest-return skill of your first year. A well-formed question gets you unblocked in two minutes; a vague one costs everyone twenty. | O32: • *How To Ask Questions The Smart Way* — http://www.catb.org/~esr/faqs/smart-questions.html (dated in tone, still correct in substance) • The XY problem — https://xyproblem.info/ | P32: Asking well is a sign of competence. Colleagues respond warmly to a clear, well-framed question — it shows you've thought about the problem and you value their time. --- --- | Q32: — | S32: Added this to the Prompt Library as "Blocker template".
H33: 2 | I33: Adopt the 30-minute rule: give it your own best effort for thirty minutes, then ask. Write it at the top of your journal. | J33: Done | K33: 46274 | L33: 46274 | M33: 0.05
H34: 3 | I34: Draft a template for asking a blocker question, containing: what I'm trying to achieve, what I've tried, what happened, what I think the issue is, what I need from you. | J34: Done | K34: 46274 | L34: 46274 | M34: 0.05
H35: 4 | I35: Ask Claude to stress-test it: *"I'm a junior product manager. Here's my template for asking a senior colleague when I'm blocked. Where would this still waste their time?"* | J35: Done | K35: 46274 | L35: 46274
H36: 5 | I36: Agree with your mentor how you'll raise blockers — channel, and expected response time. | J36: Done
A37: Module 1 · Claude Foundations — 22 hrs · 9 tasks
A38: Goal | C38: I can get reliably good work out of Claude, and I know exactly when not to trust it.
A39: About | C39: Everything after this module runs on the skills built here. You'll go from writing wishful one-liners to constructing prompts that produce usable output first time — and, just as importantly, you'll build the instinct to check. We work with AI constantly, which makes verification a professional obligation, not a nicety. ---
A40: Checkpoint | C40: Bring: your annotated prompt comparisons, your five-round debugging log, your Chat cheat sheet, your three configured Projects, your verification rule, and your prompt library. ---
A41: 1.1 | B41: 1 | C41: Learn: What a large language model actually is | D41: Learn | E41: 2 | F41: =IF(COUNTIF($J41:$J45,"Done")=5,"Done",IF(COUNTIF($J41:$J45,"Blocked")>0,"Blocked",IF(COUNTIF($J41:$J45,"To do")=5,"Not started","In progress"))) | G41: =IF(SUM($M41:$M45)=0,"",SUM($M41:$M45)) | H41: 1 | I41: Watch both videos. Don't worry if the maths goes past you; watch for the shape of the idea. | J41: Done | K41: 46274 | L41: 46274 | M41: 0.5 | N41: Before prompting well, you need a working mental model of what's happening. Not the mathematics — the behaviour, and why it fails the way it does. | O41: • *But what is a GPT?* — 3Blue1Brown: https://www.youtube.com/watch?v=wjZofJX0v4M • *Large Language Models explained briefly* — 3Blue1Brown: https://www.youtube.com/watch?v=LPZh9BOjkQs • Anthropic: *Claude's Constitution* — https://www.anthropic.com/news/claudes-constitution | P41: That last question is the important one. Everything in Task 1.8 follows from getting it right. --- --- | Q41: — | S41: Daily notes (Q&A per step): https://docs.google.com/document/d/1HlvGZ7tHs0ez33p8VfDclfm1eAKATlYmoudb2I9wxUw/edit?usp=sharing
H42: 2 | I42: Write, in five sentences and without jargon, what a language model does when you send it a message. | J42: Done | K42: 46275 | L42: 46275 | M42: 0.25
H43: 3 | I43: Paste your explanation into Claude with: *"I'm a beginner. Here's my explanation of how you work. Correct anything wrong, and tell me which of my misconceptions would most affect how well I prompt you."* | J43: Done | K43: 46275 | L43: 46275 | M43: 0.15
H44: 4 | I44: Write down the three things that most surprised you. | J44: Done | K44: 46275 | L44: 46275 | M44: 0.1
H45: 5 | I45: Answer in your journal: *given how this works, why would a model ever state something false with confidence?* | J45: Done | K45: 46275 | L45: 46275 | M45: 0.15
A46: 1.2 | B46: 1 | C46: Learn: The anatomy of a prompt | D46: Learn | E46: 3 | F46: =IF(COUNTIF($J46:$J50,"Done")=5,"Done",IF(COUNTIF($J46:$J50,"Blocked")>0,"Blocked",IF(COUNTIF($J46:$J50,"To do")=5,"Not started","In progress"))) | G46: =IF(SUM($M46:$M50)=0,"",SUM($M46:$M50)) | H46: 1 | I46: Read the overview, then the first half of best practices. | J46: Done | K46: 46275 | L46: 46275 | M46: 0.5 | N46: A good prompt has parts. Once you can name them, writing one stops being guesswork. | O46: • Prompt engineering overview — https://docs.claude.com/en/docs/build-with-claude/prompt-engineering/overview • Prompting best practices — https://platform.claude.com/docs/en/build-with-claude/prompt-engineering/claude-prompting-best-practices | P46: Keep the annotated comparisons somewhere easy to find. You'll come back to them in Task 1.4 when you start diagnosing prompts that aren't working — having your own worked examples to compare against is much faster than starting from scratch each time. --- --- | Q46: — | S46: Default skeleton: Role · Context · Task · Format · Constraints. (Also saved to Prompt Library as "Default skeleton".)
H47: 2 | I47: Write down the five components you'll use as your default skeleton: role, context, task, format, constraints. | J47: Done | K47: 46275 | L47: 46275 | M47: 0.1
H48: 3 | I48: Take a deliberately lazy prompt — *"write about design systems"* — and rewrite it using all five components. | J48: Done | K48: 46275 | L48: 46275 | M48: 0.25
H49: 4 | I49: Run both. Put the two outputs side by side in a document and annotate five concrete differences. | J49: Done | K49: 46275 | L49: 46275 | M49: 0.5
H50: 5 | I50: Repeat for two more lazy prompts of your own invention. | J50: Done | K50: 46275 | L50: 46275 | M50: 0.75
A51: 1.3 | B51: 1 | C51: Learn: Prompting techniques, properly | D51: Learn | E51: 3 | F51: =IF(COUNTIF($J51:$J55,"Done")=5,"Done",IF(COUNTIF($J51:$J55,"Blocked")>0,"Blocked",IF(COUNTIF($J51:$J55,"To do")=5,"Not started","In progress"))) | G51: =IF(SUM($M51:$M55)=0,"",SUM($M51:$M55)) | H51: 1 | I51: Read the full best-practices page, listing each technique and one line on when to use it. | J51: Done | K51: 46275 | L51: 46275 | M51: 0.5 | N51: Beyond structure there are specific techniques — examples, XML tags, step-by-step reasoning, role framing, chaining. Learn what each is for. | O51: • Prompting best practices (full) — https://platform.claude.com/docs/en/build-with-claude/prompt-engineering/claude-prompting-best-practices • Anthropic prompt library — https://docs.claude.com/en/resources/prompt-library/library • Claude Academy — https://academy.claude.com | P51: The lesson is that more technique is not automatically better. Knowing when a simple prompt is enough is part of the skill. --- --- | Q51: —
H52: 2 | I52: Browse at least ten prompts in the prompt library and note the structural patterns you see repeatedly. | J52: Done | K52: 46275 | L52: 46275 | M52: 0.25
H53: 3 | I53: Pick one task — *"summarise a client meeting into action items"* — and write four versions of the prompt: bare, with examples, with XML-tagged structure, and with explicit step-by-step instructions. | J53: Done | K53: 46275 | L53: 46275 | M53: 0.5
H54: 4 | I54: Run all four on the same fictional meeting notes and rank the outputs. | J54: Done | K54: 46275 | L54: 46275 | M54: 0.25
H55: 5 | I55: Write one paragraph on which technique earned its complexity and which didn't. | J55: Done | K55: 46275 | L55: 46275 | M55: 0.15
A56: 1.4 | B56: 1 | C56: Practise: Debugging a prompt that isn't working | D56: Practise | E56: 2 | F56: =IF(COUNTIF($J56:$J60,"Done")=5,"Done",IF(COUNTIF($J56:$J60,"Blocked")>0,"Blocked",IF(COUNTIF($J56:$J60,"To do")=5,"Not started","In progress"))) | G56: =IF(SUM($M56:$M60)=0,"",SUM($M56:$M60)) | H56: 1 | I56: Ask Claude for something genuinely hard: *"Write onboarding copy for a pet-sitting app aimed at anxious first-time users."* | J56: Done | K56: 46275 | L56: 46275 | M56: 0.1 | N56: Prompting is iterative. The skill is diagnosing *why* the output is wrong and changing exactly one thing. | O56: • Prompting best practices — https://platform.claude.com/docs/en/build-with-claude/prompt-engineering/claude-prompting-best-practices | P56: Changing three things at once is the most common beginner error — you get a better answer and learn nothing about why. --- --- | Q56: —
H57: 2 | I57: Judge the output against three criteria you write down *before* reading it. | J57: Done | K57: 46275 | L57: 46275 | M57: 0.15
H58: 3 | I58: Identify the single biggest gap between what you wanted and what you got, change one thing in the prompt to address it, and rerun. | J58: Done | K58: 46275 | L58: 46275 | M58: 0.25
H59: 4 | I59: Repeat five rounds, saving every prompt and output in order. | J59: Done | K59: 46275 | L59: 46275 | M59: 1
H60: 5 | I60: Write down the diagnosis at each round: was the problem missing context, missing constraints, wrong format, or an unclear task? | J60: Done | K60: 46275 | L60: 46275 | M60: 0.25
A61: 1.5 | B61: 1 | C61: Learn: What Claude Chat can actually do | D61: Learn | E61: 2 | F61: =IF(COUNTIF($J61:$J65,"Done")=5,"Done",IF(COUNTIF($J61:$J65,"Blocked")>0,"Blocked",IF(COUNTIF($J61:$J65,"To do")=5,"Not started","In progress"))) | G61: =IF(SUM($M61:$M65)=0,"",SUM($M61:$M65)) | H61: 1 | I61: Ask Claude directly: *"List everything you can do inside this chat interface — attachments, search, artifacts, thinking, styles, memory — and for each, one example of when a product manager would want it."* | J61: Done | K61: 46275 | L61: 46275 | M61: 0.1 | N61: Beyond text, Chat has artifacts, web search, file upload, extended thinking and more. Knowing the surface area stops you doing things the hard way. | O61: • Claude Help Center — https://support.claude.com • Claude Academy — https://academy.claude.com | P61: Step 2 is not busywork — it's your first live demonstration that a confident answer still needs checking. --- --- | Q61: — | S61: Step 3 done — tried all 6 capabilities with real questions: attachments (summarized the PMI Code of Ethics PDF), web search (latest AI-sector innovation news), artifacts (built a BMI calculator page), extended thinking (how AI integration is changing the PM skill set), styles (drafted a mentor update in my own voice), memory (recalled the Excel file name from earlier in-conversation context — noted this tests in-chat context, not true cross-session Memory).
H62: 2 | I62: Verify each claim against the Help Center, and note any that turn out to be wrong or outdated. | J62: Done | K62: 46275 | L62: 46275 | M62: 0.5
H63: 3 | I63: Try each capability at least once with a real question of your own. | J63: Done | K63: 46275 | L63: 46275 | M63: 0.75
H64: 4 | I64: Upload a PDF or image and ask three questions about it. | J64: Done | K64: 46276 | L64: 46276 | M64: 0.25
H65: 5 | I65: Write a one-page cheat sheet: capability, when to reach for it, one example prompt. | J65: Done | K65: 46276 | L65: 46276 | M65: 0.4
A66: 1.6 | B66: 1 | C66: Learn: Projects, instructions and continuity | D66: Learn | E66: 2 | F66: =IF(COUNTIF($J66:$J70,"Done")=5,"Done",IF(COUNTIF($J66:$J70,"Blocked")>0,"Blocked",IF(COUNTIF($J66:$J70,"To do")=5,"Not started","In progress"))) | G66: =IF(SUM($M66:$M70)=0,"",SUM($M66:$M70)) | H66: 1 | I66: Create three Projects: *Design Learning*, *Product Learning*, *Brief Work*. | J66: Done | K66: 46276 | L66: 46276 | M66: 0.15 | N66: Projects give Claude persistent context — reference files and standing instructions that apply to every conversation inside them. This is how you stop re-explaining yourself. | O66: • Claude Help Center — search "Projects": https://support.claude.com | P66: Projects are the difference between using Claude and having Claude set up for how *you* work. You'll live inside these three for the next six weeks. --- --- | Q66: 1.2
H67: 2 | I67: Write distinct custom instructions for each — a design critique partner behaves very differently from a PRD reviewer. | J67: Done | K67: 46276 | L67: 46276 | M67: 0.5
H68: 3 | I68: Upload relevant reference material to each (your prompt comparisons from Task 1.2, design articles you've saved). | J68: Done | K68: 46276 | L68: 46276 | M68: 0.25
H69: 4 | I69: Ask the same question in two different Projects and compare how the answers differ. | J69: Done | K69: 46276 | L69: 46276 | M69: 0.3
H70: 5 | I70: Write two sentences in your journal on what custom instructions are genuinely good for, and where they're overkill. | J70: Done | K70: 46276 | L70: 46276 | M70: 0.1
A71: 1.7 | B71: 1 | C71: Practise: Using Claude as a tutor, not an oracle | D71: Practise | E71: 3 | F71: =IF(COUNTIF($J71:$J75,"Done")=5,"Done",IF(COUNTIF($J71:$J75,"Blocked")>0,"Blocked",IF(COUNTIF($J71:$J75,"To do")=5,"Not started","In progress"))) | G71: =IF(SUM($M71:$M75)=0,"",SUM($M71:$M75)) | H71: 1 | I71: Read the Feynman technique article. | J71: Done | K71: 46276 | L71: 46276 | M71: 0.25 | N71: The highest-value use of Claude in this plan is not getting answers — it's exposing what you don't understand. This task teaches the two techniques you'll use in nearly every module from here. | O71: • The Feynman technique — https://fs.blog/feynman-technique/ • Socratic questioning overview — https://www.intechopen.com/chapters/71638 | P71: Being questioned until you reach the edge of what you know takes a little getting used to. Stick with it — it's the fastest learning available to you, and it becomes genuinely enjoyable once you trust the process. --- --- | Q71: —
H72: 2 | I72: Pick a concept you half-understand — say, why white space matters. | J72: Done | K72: 46276 | L72: 46276 | M72: 0.05
H73: 3 | I73: Explain it to Claude as if to a twelve-year-old, then prompt: *"Find every place my explanation is vague, hand-wavy or wrong. Ask me questions until I either fix it or admit I don't know."* | J73: Done | K73: 46276 | L73: 46276 | M73: 0.5
H74: 4 | I74: Keep going until you can explain it cleanly. Save the whole transcript. | J74: Done | K74: 46276 | L74: 46276 | M74: 0.75
H75: 5 | I75: Now write a reusable "tutor prompt" and a reusable "quiz me" prompt, and store both in your prompt library. | J75: Done | K75: 46276 | L75: 46276 | M75: 0.5
A76: 1.8 | B76: 1 | C76: Learn: Verification and hallucination hygiene | D76: Learn | E76: 2 | F76: =IF(COUNTIF($J76:$J80,"Done")=5,"Done",IF(COUNTIF($J76:$J80,"Blocked")>0,"Blocked",IF(COUNTIF($J76:$J80,"To do")=5,"Not started","In progress"))) | G76: =IF(SUM($M76:$M80)=0,"",SUM($M76:$M80)) | H76: 1 | I76: Read the guidance on reducing hallucinations. | J76: Done | K76: 46277 | L76: 46277 | M76: 0.25 | N76: Claude is enormously useful and sometimes confidently wrong. Professional use means knowing which claims to check and building the habit of checking them. | O76: • Reduce hallucinations — https://platform.claude.com/docs/en/test-and-evaluate/strengthen-guardrails/reduce-hallucinations • Claude's Constitution — https://www.anthropic.com/news/claudes-constitution | P76: Using AI well is exactly what's expected here. What makes you trusted with it is the checking — the rule you write today is what lets you use Claude confidently on client work. --- --- | Q76: —
H77: 2 | I77: Ask Claude five factual questions where you can independently verify the answers — statistics, dates, whether a specific tool has a specific feature. | J77: Done | K77: 46277 | L77: 46277 | M77: 0.2
H78: 3 | I78: Check every answer against a primary source. Record what was right, wrong, or subtly off. | J78: Done | K78: 46277 | L78: 46277 | M78: 0.5
H79: 4 | I79: Write your personal verification rule: which categories of claim you will *always* check. Suggested starting set — numbers, dates, names, URLs, legal or medical claims, and anything you're about to put in front of a client. | J79: Done | K79: 46277 | L79: 46277 | M79: 0.15
H80: 5 | I80: Pin that rule somewhere you'll see it daily. | J80: Done | K80: 46277 | L80: 46277 | M80: 0.1
A81: 1.9 | B81: 1 | C81: Build: Your personal prompt library | D81: Build | E81: 3 | F81: =IF(COUNTIF($J81:$J85,"Done")=5,"Done",IF(COUNTIF($J81:$J85,"Blocked")>0,"Blocked",IF(COUNTIF($J81:$J85,"To do")=5,"Not started","In progress"))) | G81: =IF(SUM($M81:$M85)=0,"",SUM($M81:$M85)) | H81: 1 | I81: Create a document called *My Prompt Library*, organised by purpose: Learn, Critique, Ideate, Write, Analyse, Review. | J81: Done | K81: 46278 | L81: 46278 | M81: 0.5 | N81: Turn everything from this module into a reusable asset you'll add to for the rest of your career. | O81: • Anthropic prompt library — https://docs.claude.com/en/resources/prompt-library/library • Your own saved prompts from Tasks 1.2–1.8 | P81: Come back to this at the end of every module and add what worked. By Module 9 it will be the most useful document you own. --- --- | Q81: —
H82: 2 | I82: Seed it with at least twelve prompts from this module — tutor, quiz, critique, comparison, debate, verification. | J82: Done | K82: 46278 | L82: 46278 | M82: 1
H83: 3 | I83: Give each a title, a one-line "use this when", and the prompt text with `[BRACKETS]` marking what to swap. | J83: Done | K83: 46278 | L83: 46278 | M83: 0.75
H84: 4 | I84: Ask Claude to review it: *"Here's my prompt library. Which of these are weak, which overlap, and what obvious gaps does a product manager have?"* | J84: Done | K84: 46278 | L84: 46278 | M84: 0.25
H85: 5 | I85: Act on the feedback and save the library into your *Design Learning* Project. | J85: Done | K85: 46278 | L85: 46278
A86: Module 2 · Discovery and Problem Definition — 20 hrs · 7 tasks
A87: Goal | C87: I can take a vague request from a client and turn it into a problem worth solving.
A88: About | C88: Products don't start with a feature request. They start with a person who has a problem, and a client who has described that problem imperfectly. This module gives you the loop we use to get from a vague brief to a problem statement a team can build against — and by the end you'll have run it once on a real brief. ---
A89: Checkpoint | C89: Bring: your interview questions and write-up, POV statement and HMW set, ideation output, fidelity table, usability script and findings, and the full PawPal document. ---
A90: 2.1 | B90: 2 | C90: Learn: The design thinking process, end to end | D90: Learn | E90: 2 | F90: =IF(COUNTIF($J90:$J94,"Done")=5,"Done",IF(COUNTIF($J90:$J94,"Blocked")>0,"Blocked",IF(COUNTIF($J90:$J94,"To do")=5,"Not started","In progress"))) | G90: =IF(SUM($M90:$M94)=0,"",SUM($M90:$M94)) | H90: 1 | I90: Read both, then draw the five stages on paper with an arrow between each — including the loops backwards. | J90: Done | K90: 46279 | L90: 46279 | M90: 0.5 | N90: Get the map before the territory. Five stages, what each is for, and why skipping any of them shows up later as expensive rework. | O90: • IxDF: *5 Stages in the Design Thinking Process* — https://www.interaction-design.org/literature/article/5-stages-in-the-design-thinking-process • IxDF: *Design Process* topic hub — https://www.interaction-design.org/literature/topics/design-process | P90: The honest answer to that last question is usually "Empathise" — jumping to solutions feels productive. Notice the urge; it doesn't go away, you just learn to overrule it. --- --- | Q90: —
H91: 2 | I91: For each stage write: its purpose, its output, and what typically gets missed when it's rushed. | J91: Done | K91: 46279 | L91: 46279 | M91: 0.5
H92: 3 | I92: Ask Claude: *"I'm learning design thinking. Here's my one-line summary of each stage. Give me a real example of a product that clearly skipped one of these stages, and what went wrong as a result."* | J92: Done | K92: 46279 | L92: 46279 | M92: 0.15
H93: 4 | I93: Pick one app you use daily and guess which stage its team invested most in. | J93: Done | K93: 46279 | L93: 46279 | M93: 0.2
H94: 5 | I94: Journal: which stage do you think you'll personally be tempted to skip, and why? | J94: Done | K94: 46279 | L94: 46279 | M94: 0.15
A95: 2.2 | B95: 2 | C95: Practise: Empathise — talking to users | D95: Practise | E95: 3 | F95: =IF(COUNTIF($J95:$J99,"Done")=5,"Done",IF(COUNTIF($J95:$J99,"Blocked")>0,"Blocked",IF(COUNTIF($J95:$J99,"To do")=5,"Not started","In progress"))) | G95: =IF(SUM($M95:$M99)=0,"",SUM($M95:$M99)) | H95: 1 | I95: Read both NN/g articles, noting the difference between asking about past behaviour and asking about hypothetical future behaviour. | J95: Done | K95: 46279 | L95: 46279 | M95: 0.25 | N95: The first stage is understanding the person, not the problem. Learn to ask questions that surface what people actually do rather than what they think they should say. | O95: • NN/g: *User Interviews 101* — https://www.nngroup.com/articles/user-interviews/ • NN/g: *Open-Ended vs. Closed-Ended Questions* — https://www.nngroup.com/articles/open-ended-questions/ • Brief A: PawPal — Appendix A | P95: The hardest part of an interview is silence. When they stop talking, count to three before you speak — the second half of an answer is usually the useful half. --- --- | Q95: —
H96: 2 | I96: Read Brief A (PawPal) in Appendix A. | J96: Done | K96: 46279 | L96: 46279 | M96: 0.15
H97: 3 | I97: Write ten interview questions for a prospective PawPal user. At least seven must ask about something they actually did. | J97: Done | K97: 46279 | L97: 46279 | M97: 0.5
H98: 4 | I98: Ask Claude to critique them: *"Here are ten user-interview questions. Mark each as leading, hypothetical, double-barrelled, or good — and rewrite the weak ones."* | J98: Done | K98: 46279 | L98: 46279 | M98: 0.15
H99: 5 | I99: Run a fifteen-minute interview with your mentor or a colleague playing a pet owner. Take notes without interrupting, then write up the three most surprising things you heard. | J99: Done | K99: 46280 | L99: 46280 | M99: 0.5
A100: 2.3 | B100: 2 | C100: Practise: Define — turning research into a problem statement | D100: Practise | E100: 3 | F100: =IF(COUNTIF($J100:$J104,"Done")=5,"Done",IF(COUNTIF($J100:$J104,"Blocked")>0,"Blocked",IF(COUNTIF($J100:$J104,"To do")=5,"Not started","In progress"))) | G100: =IF(SUM($M100:$M104)=0,"",SUM($M100:$M104)) | H100: 1 | I100: Read all three. | J100: Done | K100: 46280 | L100: 46280 | M100: 0.3 | N100: Raw research is a pile of quotes. Defining is the act of turning that pile into one sentence a team can build against. | O100: • IxDF: *Define the Problem* — https://www.interaction-design.org/literature/topics/define-the-problem • NN/g: *Affinity Diagramming* — https://www.nngroup.com/articles/affinity-diagram/ • IDEO / d.school: *How Might We* — https://www.designkit.org/methods/how-might-we | P100: A good problem statement takes some nerve, because it deliberately closes doors. If yours could apply to any app, it's worth another pass. --- --- | Q100: — | S100: The last link is not working, the correct link is: https://www.designkit.org/methods/how-might-we.html
...

Sheet Practice Briefs
A1: Brief | B1: Used in | C1: The brief, as the client wrote it | D1: What's deliberately missing | E1: Why this brief
A2: Brief A · PawPal | B2: Module 2 | C2: We're a small team in Ahmedabad and we want to build an app for pet sitting. The idea is that pet owners can find someone nearby to look after their pet when they travel. There are a lot of these apps abroad but nothing good for the Indian market. Our main worry is trust — people are nervous about handing their dog to a stranger. We want it to feel safe. We're thinking about reviews and maybe some kind of verification. We'd want owners to be able to book someone quickly, see who's available, and message them. Sitters should be able to set their availability and rates. Payments through UPI. We have a small budget and want something in the market within four months. | D2: who the sitters are and how they're recruited, what "verification" means, what happens when something goes wrong, whether this is for boarding or home visits, and how the two sides of the marketplace get seeded.
A3: Brief B · Harvest Hub | B3: Modules 4, 5 and 6 | C3: We distribute fresh produce to about 200 restaurants and small grocers across three cities. Right now our ops team runs everything on WhatsApp and a shared spreadsheet, and it's falling apart. Orders get missed. Nobody knows what stock we have until someone walks into the cold storage. We need an internal admin system. The ops team should be able to see incoming orders, check stock, assign deliveries to drivers, and know what's late. Our warehouse manager wants to update inventory as things come in and go out. Our owner wants to see how the business is doing without asking anyone. The ops team is five people, aged 25 to 55, not especially technical. They work on laptops in the warehouse office. Some of them are much faster on the spreadsheet than they'd be on a new system, and they've told us so. Produce is perishable — an order that's a day late is often worthless. That's the thing that costs us the most. | D3: how orders currently arrive, whether drivers need anything, what "how the business is doing" means to the owner, existing systems it must talk to, and what happens when stock runs out mid-order. | E3: dense, information-heavy, used all day by non-enthusiastic users. This is what most of our client work actually looks like — and the requirements are far harder than the screens.
A4: Brief C · ClaimLens | B4: Modules 6 and 8 (capstone) | C4: We're a mid-sized insurance company handling around 4,000 motor claims a month. Each claim comes in with a form, photos, sometimes a police report, sometimes a garage estimate. Our adjusters open each one, read everything, decide whether it's straightforward or needs investigation, and route it accordingly. It takes too long. Our adjusters spend most of their day on claims that were obviously routine, which means the complicated ones sit in a queue. We want an AI-assisted triage console. When a claim arrives, the system should read what's in it, flag anything unusual, suggest a route, and let the adjuster confirm or override. We'd also like adjusters to be able to search across past claims and policy documents in plain language rather than by claim number. Our adjusters have been doing this for years and some of them have been here two decades. A few of them are worried this is about replacing them. Our compliance team needs every decision to be auditable — if a claim was routed a certain way, we need to be able to show why. Regulator-facing, so we can't get this wrong. | D4: what "unusual" means, what the adjusters currently find hardest, what happens when the AI is wrong, what the audit trail must contain, accessibility requirements, and how the system is introduced to a sceptical team. | E4: it's dense, it's regulated, it has real humans with real anxieties, and its central feature is probabilistic. Every one of those is a design problem you'll meet here.

Sheet Prompt Library
A1: Prompt | B1: Use this when | C1: Prompt text | D1: My notes
A2: Tutor | B2: use when you half-understand something. | C2: I'm learning `[CONCEPT]` as a junior product manager. I'll explain it as I understand it. Find every place my explanation is vague, hand-wavy or wrong, and ask me questions until I either fix it or admit I don't know. Don't give me the answer straight away. | D2: Structural pattern: placeholder [CONCEPT]; frames the user's own role ("junior product manager"); blocks the lazy shortcut of Claude just giving the answer; ends on a repeatable Q&A loop rather than a one-off output.
A3: Quiz | B3: use before a checkpoint. | C3: Quiz me on `[TOPIC]`. Ten questions, one at a time, waiting for my answer before the next. Mix recall and application. At the end, tell me which two areas I should revisit. | D3: Structural pattern: placeholder [TOPIC]; blocks the lazy shortcut of dumping all questions at once ("one at a time, waiting for my answer"); ends on a specific, bounded deliverable (two areas to revisit).
A4: Critique | B4: use on any screen. | C4: Here's a screen our designer has produced: `[DESCRIPTION OR IMAGE]`. Critique it as a product lead would — hierarchy, spacing, alignment, contrast, missing states, accessibility. Be specific. Separate what's objectively wrong from what's your preference. | D4: Structural pattern: placeholder [DESCRIPTION OR IMAGE]; assigns Claude a role ("as a product lead would"); blocks the lazy shortcut of vague or opinion-blended feedback ("be specific, separate objective from preference"); deliverable spans named criteria (hierarchy, spacing, etc.).
A5: Self-critique check | B5: use after your own review. | C5: Here's my critique of a screen. What did I miss, and where am I stating personal preference as if it were an established principle? | D5: Structural pattern: no placeholder — relies on the prior critique already in the conversation; no explicit role; blocks the lazy shortcut of treating personal preference as objective principle; ends on two pointed, specific questions.
A6: Diverge | B6: use when ideating. | C6: Here's my problem statement: `[STATEMENT]`. Give me 25 distinct solution directions, including at least 5 that are deliberately impractical. Don't evaluate any of them. | D6: Structural pattern: placeholder [STATEMENT]; no role; blocks the lazy shortcut of premature judgment ("don't evaluate any of them"); deliverable is a specific count (25, incl. 5 deliberately impractical).
A7: Devil's advocate | B7: use before committing to a decision. | C7: I've decided `[DECISION]` because `[REASONING]`. Argue the strongest possible case against it. Then tell me what evidence would settle the question. | D7: Structural pattern: two placeholders [DECISION]/[REASONING]; implicit adversarial role ("strongest possible case against it"); blocks a weak/strawman counterargument; ends on a specific, actionable follow-up (evidence that would settle it).
A8: Play the developer | B8: use before handoff. | C8: You're a frontend developer receiving this specification. Ask me every question you'd need answered before you could start building. | D8: Structural pattern: no placeholder — relies on a spec already shared in context; explicit role ("you're a frontend developer"); blocks the lazy shortcut of asking only one surface-level question ("every question"); deliverable is an exhaustive question list.
A9: Play the client | B9: use before a presentation. | C9: You're a thorough client who wrote the original brief. I'll present my work. Ask me the three hardest questions, including at least one about cost or timeline. | D9: Structural pattern: no placeholder; explicit role ("thorough client"); blocks softball questions ("hardest questions"); deliverable is a bounded count (three) with a sub-constraint (at least one on cost/timeline).
A10: Requirements check | B10: use on any spec. | C10: Review this document. Which requirements are actually solutions in disguise? Which are vague enough that two developers would build different things? | D10: Structural pattern: no placeholder — relies on "this document" from context; no role; the two diagnostic questions themselves block a generic "looks fine" response; deliverable is two specific requirement-quality categories.
A11: Verify | B11: use on anything factual. | C11: For each factual claim in your last response, tell me how confident you are and what I should independently check before relying on it. | D11: Structural pattern: no placeholder — refers to "your last response" from context; no role; forces per-claim granularity instead of one blanket confidence statement; deliverable is confidence + a specific check, per claim.
A12: Compare techniques | B12: use when learning a tool. | C12: I'm going to give you four versions of a prompt for the same task. Tell me which is best and, more importantly, why the extra complexity in the others did or didn't earn its place. | D12: Structural pattern: no placeholder — the four prompt versions arrive in a later turn; no role; blocks a bare ranking without justification ("more importantly, why"); deliverable is a ranking plus a complexity/value judgment.
A13: Reduce | B13: use when your work is bloated. | C13: Here's my `[DOCUMENT / SCREEN / FLOW]`. What could I remove entirely without losing anything the user needs? Be aggressive. | D13: Structural pattern: placeholder [DOCUMENT / SCREEN / FLOW]; no role; blocks a timid, minimal-cuts answer ("be aggressive"); deliverable is an implicit list of removable items.
A14: [ add your own below ]
A15: Blocker template | B15: use when you're stuck and about to ask someone for help. | C15: Urgency: [blocking me right now / can wait until EOD / no rush] What I'm trying to achieve: [one sentence — the actual goal] What I've tried: [2-3 bullets max, most recent first] What happened: [the actual result — error, output, behavior — not just 'it didn't work'] What I think the issue is, and what I've ruled out: [best guess + what you already checked and why it's not that] Attached: [link, screenshot, or log, if relevant] What I need from you, and in what form: [a specific ask — e.g. 'a yes/no', 'review this one line', 'point me to who owns X' — not just 'sanity check'] | D15: For blocker messages to a mentor/colleague. v2 — tightened after Claude stress-tested v1 (Step 4, Task 0.6): added urgency, bounded length, ruled-out reasoning, an attachment slot, and a specific answer format. Structural pattern: the most placeholder-dense entry of the 14 (six bracketed fields) — functions as a fill-in-the-blank message template rather than a prompt that generates new content.
A16: Default skeleton | B16: use as your default checklist before writing any prompt, so you don't skip a part. | C16: Role · Context · Task · Format · Constraints | D16: Role = who Claude should act as. Context = background it needs. Task = the actual instruction. Format = how the output should look. Constraints = rules/limits it must follow. Structural pattern: the outlier of the 14 — a five-part checklist/framework to consult before writing a prompt, not a fill-in-the-blank prompt itself; no bracketed placeholders.
A17: My Tutor | B17: use when you want Claude to interrogate your own explanation of something you half-understand, rather than react to a lazy request. | C17: Your role is direct me towards the right understanding towards a concept [CONCEPT] which is half understood by me. Your task is to find every vague, hand-wavy or wrong part and ask follow-up questions about it, until its tightened up or I admit that I dont know about it. Write the answer in a multiple paragraph format, i.e one paragraph for each issue, never correct me or hand over the answer. | D17: Built during Task 1.7 by having Claude interrogate a live explanation ("why PMs use Jira") across three rounds of questions until it was tightened up. Structural pattern: placeholder [CONCEPT]; blocks Claude from correcting directly or handing over the answer; explicit format rule for multi-issue responses (one paragraph per issue); stopping condition is either/or (tightened up OR admit not knowing), not both. Sits alongside the pre-built "Tutor" template above — built independently, landed on the same core shape.
A18: Quiz Me (mine) | B18: use when you want Claude to actively test your understanding of a topic, rather than you supplying the explanation first. | C18: You are a Quiz Master who generates questions about a topic and judges my answers on the topic [TOPIC]. You need to ask one question at a time, explain the correct answer if I am wrong, move on if I am right; after a few correct in a row, ask if I want harder questions; keep going until you are confident that I understand the concept. Label each question as 'Q1', 'Q2' etc. Never drift from the core topic and never reveal the correct answer before I have replied. | D18: Built during Task 1.7 alongside the Tutor prompt above, as the inverse case — Claude initiates the questions instead of reacting to an explanation. Structural pattern: placeholder [TOPIC]; role covers both halves of the job (asks questions AND judges answers); branching task logic (explain if wrong / advance if right / offer harder questions after a streak); adaptive difficulty is a deliberate added behavior, not a constraint; the exit condition is Claude's own confidence in my understanding, not my self-declared confidence — an early draft accidentally let the quiz-taker self-certify, which would have defeated the point.
A19: Extract & Build from Attachment | B19: You need to extract something specific from an attached file and use it to build a new output — not locked to any one output type. | C19: From the attached [FILE], extract [WHAT TO PULL OUT] and use it to build [OUTPUT TYPE]. | D19: Built during Task 1.9 from Task 1.5's Attachments example; renamed and broadened during the Step 4 library review (originally titled "Web Page format extraction" and hard-coded to a web-page output). Structural pattern: three placeholders — [FILE], [WHAT TO PULL OUT], [OUTPUT TYPE] — generalizes beyond web pages to any extract-then-build task.
A20: Quick Topic Update via Web Search | B20: You need a quick update on a topic. | C20: Give me the latest updates regarding [TOPIC]. | D20: Built during Task 1.9 from Task 1.5's Web search example. Structural pattern: single placeholder [TOPIC]; generalized from a narrow example (AI automation in infrastructure) into a topic-agnostic template.
A21: Build & Test an Artifact | B21: You need to build and test a template before making the final product. | C21: Create an [Artifact Type] which does this [Function] based on this [input]. | D21: Built during Task 1.9 from Task 1.5's Artifacts example; renamed during the Step 4 library review (originally titled "Side panel feature", which described the UI mechanism rather than the prompt's function). Structural pattern: three placeholders — [Artifact Type], [Function], [input] — separating what's built, what it does, and what it takes in, generalized from a one-off compound-interest calculator.
A22: Multi-Factor Tradeoff Analysis | B22: A decision has more than one dimension (cost, risk, timeline, etc.) and you need them synthesized into a single call. | C22: Considering [FACTOR A], [FACTOR B], and [FACTOR C], what's the best way to approach [SITUATION]? | D22: Built during Task 1.9 from Task 1.5's Extended Thinking example. Reshaped from a single-topic explainer into a true multi-factor tradeoff prompt so the prompt text actually matches the reasoning for reaching for Extended Thinking. Structural pattern: three factor placeholders plus [SITUATION].
A23: Write in My Voice | B23: You need the output to sound like you actually wrote it — tone, phrasing, and format included. | C23: Write [MESSAGE TYPE] to [RECIPIENT] about [TOPIC], as if I wrote it myself — it shouldn't sound like AI-written content. | D23: Built during Task 1.9 from Task 1.5's Styles example. Structural pattern: three placeholders — [MESSAGE TYPE], [RECIPIENT], [TOPIC] — generalized from a single stakeholder-email example.
A24: Recall & Summarize | B24: You need Claude to pull together everything established earlier in this conversation, instead of re-explaining it. | C24: Summarize what we've covered on [TOPIC] over [TIMEFRAME]. | D24: Built during Task 1.9 from Task 1.5's Memory example. Note (per the original cheat sheet): this tests in-chat/in-conversation recall, not true cross-session Memory. Structural pattern: two placeholders — [TOPIC] and [TIMEFRAME].
A25: Explain a Concept to an Audience | B25: You need to introduce an unfamiliar concept to someone with zero background, in a tight, structured way. | C25: Role: A PM explaining [CONCEPT] to [AUDIENCE]. Context: For someone who's never encountered [CONCEPT] before and needs a foundational understanding. Task: Define [CONCEPT] clearly and [WHAT TO COVER — e.g. give 2-3 examples / walk through the lifecycle]. Format: A definition followed by [STRUCTURE — e.g. bulleted examples / step-by-step breakdown]. Constraints: Under 200 words, no jargon, [ADDITIONAL CONSTRAINT]. | D25: Built during Task 1.9 from Task 1.2's Role-Context-Task-Format-Constraints exercise (the automation and tickets rewrites). A concrete instantiation of the Default skeleton (row 16) for one specific job — explaining a concept to an audience — rather than the bare framework itself. Structural pattern: five placeholders, one per skeleton slot.
A26: Step-by-Step Meeting Summarizer | B26: You have raw meeting notes and need them turned into a clear action list fast. | C26: 1. Go through [MEETING NOTES]. 2. Extract the action items out of it. 3. Present it in [OUTPUT FORMAT — e.g. heading with bullet list]. | D26: Built during Task 1.9 from Task 1.3's four-version prompting-technique experiment (bare / with examples / XML-tagged / step-by-step) for 'summarise a client meeting into action items.' The step-by-step version was judged to earn its complexity without extra scaffolding overhead. Structural pattern: two placeholders — [MEETING NOTES] and [OUTPUT FORMAT].
... A31: Iterative Prototype Build — Protect the Core Requirement | B31: You're refining a design or prototype over many rounds and there's one requirement that has to survive every round, not just the first one. | C31: Build [SCREEN/COMPONENT] with the following structure and hierarchy: [DETAILS]. Non-negotiable requirement, checked on every round from now on — including rounds that don't mention it: [THE SPECIFIC REQUIREMENT, e.g. "Log out must stay visually distinct in kind, not just position, from every other row on this screen"]. Before applying any requested change, check whether it would weaken this requirement, even indirectly — removing a separator, making a uniform style change that happens to erase a contrast, etc. If a requested change would weaken it, apply the change but flag the tradeoff explicitly rather than doing it silently. At the end of every round, state in one line whether the non-negotiable requirement still holds. | D31: Built during Task 4.6, Step 5, after watching a Log-out safety requirement quietly erode over 10 rounds of the Claude Design refinement — two unrelated, locally-reasonable fixes (a text-wrap fix, a gradient-consistency fix) combined to undo it. Structural pattern: turns a requirement from one-time prose in the build prompt into a standing check applied to every future round, with an explicit instruction to flag rather than silently apply any change that would weaken it.

Sheet Journal
A1: Rule: try on my own for 30 minutes before asking anyone for help — check resources, test my best guess — then ask if still stuck. Rule: always verify medical claims, education industry claims, business numbers, dates, location, and citation sources before trusting them. Rule: Before picking a fidelity, name the single specific uncertainty you're actually trying to resolve — then ask "would this artifact even let me test that, or would it only test something that looks related?" — and pick the lowest fidelity that genuinely resolves it.
A2: Date | B2: Module | C2: Task ID | D2: What I made today | E2: What confused me | F2: What I want to ask | G2: One thing I'd do differently | H2: Weekly review (Fridays)
A3: 46272 | B3: 0 | C3: 0.1 | D3: Read 15 policies and made notes of all the unfamiliar terms, also clarified some doubts related to policy to the mentor (Nidhi). | E3: Some unfamiliar coorporate terminologies. | F3: Want to know more about the softwares that the company uses for cloud infrastructure management like AWS, Azure, GCP etc. What are the services offered by each of them? What is the speciality of each software? What is the reason relying on multiple softwares instead of one or two? Comparison analysis between them. | G3: Would make notes while reading the policies. | H3: Weekly: the three things I understand better than Monday · the one thing I have been avoiding · what I want more of next week · what I want less of next week
A4: 46273 | B4: 0 | C4: 0.2 | D4: Went through all the company policies and set up Claude by creating a folder structure on my machine first and then asked my mentor about which internal tools, I have access to: Cowork and Claude design | E4: I was asked to switch on code execution and file creation feature under Settings > Capabilities but I couldn't find the feature there. | F4: I created the folder structure on my machine through Claude itself, I am wondering if there is also a manual way of doing so. Also, how Cowork and Claude Design is useful to me. | G4: When I wasn't able to find the switch to code execution/file creation, I could have looked at the Claude Help Center.
A5: 46273 | B5: 0 | C5: 0.3 | D5: Set up a Claude Project called Phase 1 Learning Journal, added custom instructions telling it to ask me one sharp question about whatever confused me instead of reassuring me, copied the journal template into 01-Journal, then wrote today's entry covering Tasks 0.1 and 0.2 and pasted it in to see what it would ask back. | E5: Claude pushed back on the Sept 9 entry — I said I couldn't find the code-execution/file-creation toggle under Settings > Capabilities, but I never actually checked whether that's a personal setting or an org-admin control I don't have permission to flip. | F5: Who on my account actually has admin rights to flip org-level settings like that, so I know who to ask instead of assuming a feature doesn't exist? | G5: Before saying a feature "isn't there," I'd check whether it's gated behind a permission level I don't have, rather than assuming it's missing entirely.
A6: 46274 | B6: 0 | C6: 0.4 | D6: Before: 1. The progress has been smooth so far but I feel that this portion [of work] is attracting the possibility of [threat] therefore I urge [my superior] to take a close look at it and correct me if I am wrong. 2. This thing should have been operated like [the method] but I unknowningly did this [mistake] instead, I urge the concerned authorities to take immediate look at it. I deeply express my apologies and would be careful next time. when you do the major work but struggle to stand up for yourself and hBeence let someone else take the credit of your work. 3. Since day one of being a part of this project, I have poured all my energy into it and not only completed the tasks assigned to me on time but also expanded my boundaries and took up some extra work. I just wanted to make my contribution in the project clear because initially I was struggling a bit to stand up for myself. After:1. Flagging something in [specific portion]: [what you noticed]. If that's right, it could lead to [specific consequence] because [your reasoning]. Could we confirm [specific thing] before [deadline/next step]? Wanted to raise it while there's still time to adjust — happy to be wrong here. 2. I made a mistake on [task]: I used [method B] instead of [method A]. Impact so far: [who/what's affected]. I've already [contained it by doing X]. Going forward I'm going to [specific change, e.g. "confirm the method with you before starting" or "add a checklist step for this"]. 3. Flagging now so we can decide [next step] before [deadline]. Wanted to make sure the record's clear on [project]: I led [specific deliverable], and also took on [specific deliverable] outside my original scope. Happy to walk through the details anytime. Going forward, I'd like to present my own updates on this work so ownership is clear.
A7: 46274 | B7: 0 | C7: 0.5 | D7: Read the ethics/dark-pattern articles, then pulled three dark patterns I've actually run into in Zomato: free-delivery tags tied to hidden thresholds that silently revert to a delivery fee, extra platform/handling fees that creep back in even when delivery is free, and Gold-membership prompts that fire right after I've already qualified for free delivery. Wrote the business-goal-vs-user-cost pair for each (forced buying, hidden costs, nagging into a subscription), then redesigned the third: only show the Gold prompt when I'm actually ineligible for free delivery, not every time I open the app. Debated it with Claude — argued both the case for it being acceptable business practice and the case against. | E7: The case for it being acceptable business practice was the harder one to counter — the "it's just normal upsell timing, not manipulation" argument held up better than I expected. | F7: Where's the actual line between this and something like Amazon pitching Prime at checkout? Claude's answer was that Zomato manufactures a false sense of losing something I already have — but how would I actually test for that in my own product before shipping it? | G7: I'd have picked a dark pattern I hadn't already half-justified in my head, so the redesign forced a real trade-off instead of an obvious fix.
A8: 46275 | B8: 1 | C8: 1.1 | D8: Built on yesterday's videos by writing my own five-sentence, jargon-free explanation of what a language model does, then handed it to Claude for correction. Got pushback on three things — tokens aren't strictly alphanumeric, "weights" conflates model weights with attention weights, and "more layers = more refined response" isn't quite right — plus the big one: generation happens one token at a time, not all at once. Worked through why that means a model can state something false with full confidence: its "confidence" is really a measure of how plausible the phrasing looks, not a fact-check, and once it's committed to a wrong detail it just keeps building a fluent continuation around it rather than catching the error. | E8: The distinction between model weights (fixed, learned in training) and attention weights (dynamic, per-input) — I'd been treating "weights assigned to tokens" as one thing when it's actually two different concepts. | F8: Does sampling settings like temperature change how 'committed' a model gets to a wrong path once it's started one, or is that only about how random vs. predictable the token choice is? | G8: I'd have tried reasoning through the autoregressive point myself before Claude's scaffolding got me there — I got it eventually, but only after being walked through it directly.
A9: 46275 | B9: 1 | C9: 1.2 | D9: Wrote down the five-component "default skeleton" (Role · Context · Task · Format · Constraints), then used it to rewrite three deliberately lazy prompts — "write about design systems," "what is automation?," and "what are tickets?" — ran each lazy/crafted pair side by side and annotated five concrete differences for each (audience framing, AI-specific vs. generic content, structured vs. plain output, bounded length vs. none, plain language vs. industry jargon). Saved the skeleton itself to the Prompt Library as "Default skeleton." | E9: Wasn't sure at first where "role, context, task, format, constraints" should actually live — in the prompt text itself, a template, or somewhere else — until it clicked that it's a checklist to run through before writing any prompt, not a literal section header. | F9: Since the Default skeleton is a checklist rather than a prompt template like the others in the library, should it be its own separate thing, or is it fine sitting in the same list as the actual prompts? | G9: For both the automation and tickets prompts I built the five components one at a time with help — I'd have tried writing at least one crafted prompt from scratch solo, to test if I'd actually internalized the skeleton.
A10: 46275 | B10: 1 | C10: 1.3 | D10: Learned the actual prompting techniques from the best-practices page, then wrote four versions of a "summarise a client meeting into action items" prompt — bare, with examples, XML-tagged, and step-by-step — ran all four against a fictional client meeting, and ranked the outputs: bare came out on top, followed by step-by-step, then XML-tagged, with the with-examples version failing outright. | E10: Thought "with examples" meant giving one narrow literal example ("if X, write Y") rather than something that generalizes a pattern — took two attempts to actually get an example-based prompt that demonstrated a repeatable structure instead of a single hard-coded case. | F10: If a single example locks a prompt onto one narrow case, how many examples (or how varied) do they actually need to be before the pattern generalizes reliably? | G10: I'd have tested my few-shot prompt against a slightly different action item before ranking it, instead of judging it only on the exact case it was written around — would've caught the narrowness sooner.
A11: 46275 | B11: 1 | C11: 1.4 | D11: Ran a genuinely hard prompt (pet-sitting onboarding copy for anxious first-time users), then debugged it across five deliberate one-change-at-a-time rounds — adding a trust signal, swapping in positive language, cutting anxiety-triggering phrases, adding a brand-values line, and opening with a use-case question — and diagnosed each fix as missing constraints, missing constraints, missing constraints, missing context, and wrong format, respectively. | E11: Assumed adding content alongside a data point still counted as one change — got pushback that this actually tangles two variables together, so you can't tell which one caused any improvement. | F11: When a diagnosis could genuinely fall into two categories at once (like the brand-values line being either missing context or missing constraint), is there a rule of thumb for picking one, or is it fine to note both? | G11: I was supposed to write my three judging criteria before reading the first output, but wrote them after seeing it — which risks shaping the criteria around what I'd already noticed instead of judging blind.
A12: 46276 | B12: 1 | C12: 1.6 | D12: Set up the three Claude Projects (Design Learning, Product Learning, Brief Work) with distinct custom instructions and their own reference material — the Task 1.2 prompt-comparison file for Product Learning, the Task 1.4 PawCare debugging file for Brief Work, and four downloaded UX/design articles for Design Learning. Tested the same question (whether to gate signup behind email verification) across all three and compared the results: Product Learning reasoned as a business trade-off with competitor examples, Design Learning reasoned from UX principles and pushed back before agreeing, and Brief Work reasoned directly from my own PawCare project history via its uploaded file — while all three converged on essentially the same underlying recommendation. | E12: Whether the differences I saw across the three answers were really coming from the custom instructions, or mostly from which reference files were loaded — Brief Work's answer felt grounded specifically because of the uploaded file, not just its role description. | F12: Is there a way to test a Project's custom instructions in isolation from its reference files, to know which one is actually responsible for a given difference in the output? | G12: I'd have run a fourth version of the same question with no custom instructions and no files at all, as a true baseline, before concluding what the instructions specifically were adding.
A13: 46277 | B13: 1 | C13: 1.8 | D13: Completed Task 1.8 — asked Claude 5 verifiable factual questions, checked the answers against primary sources, and wrote my personal verification rule (pinned above). | E13: All five factual answers actually checked out correct against primary sources, so the exercise never caught an outright wrong answer. Two of the five were softer than the others, though — "ideal BMI range" doesn't have one universal number (it varies by guideline), and the Claude multi-agent-roles question depended on how strictly I read "without human interference." That fuzziness, not an actual error, is what really shaped which categories went into my verification rule. | F13: Should my verification rule also cover claims that are correct but context-dependent (like the BMI range), or is it meant only for claims that are flatly right or wrong? | G13: I'd pick a more deliberately mixed set of five questions next time — a couple of quick lookup facts, one genuinely contested/nuanced topic, and one about a fast-changing product feature — instead of mostly straightforward facts that were always likely to check out, so the exercise actually had a chance of catching a real gap.
A14: 46278 | B14: 1 | C14: 1.9 | D14: Completed Task 1.9 — built out the Prompt Library to 27 entries (12 self-built from Tasks 1.2–1.8), had Claude review it for weak spots, overlaps, and gaps, acted on that feedback (two renames, two new entries — RICE Prioritization and What's Notable in This Data), and saved the organized "My Prompt Library" doc into the Design Learning Project. Also went back and filled in the missing round-by-round prompt/output record for Task 1.4 Step 4 in the tasks doc, and backfilled estimated per-step hours across all of Module 1. | E14: I hadn't actually kept a full round-by-round record of Task 1.4 Step 4 when I did it, so when Task 1.9's review surfaced the gap, I had to reconstruct the round 5 prompt from memory rather than just pulling it up. I also got tripped up on the difference between renaming/broadening an existing prompt versus adding a genuinely new one when acting on Claude's review feedback — several of the "gaps" could have gone either way. | F14: The library already has two near-duplicate pairs (Tutor/Quiz vs. My Tutor/Quiz Me (mine)) that I built at different points without noticing the overlap. How do I decide, later, whether to merge near-duplicates like that or keep both because the small differences are actually worth preserving? | G14: I'd have saved the full round-by-round prompt/output record for Task 1.4 Step 4 at the time I actually ran it, instead of relying on memory to reconstruct it during a later task's review.
A15: 46279 | B15: 2 | C15: 2.1 | D15: Completed Task 2.1 — read up on the design thinking process end to end and drew the five stages with the backward loops on paper, then wrote a purpose/output/failure-mode table for each stage. Asked Claude for a real example of a product that skipped a stage — Juicero, which skipped a proper Define step by letting the business model (proprietary juice packets) override the actual problem statement (fresh juice, low effort). Picked Instagram to guess which stage its team invested most in — first guessed Ideate, reconsidered after pushback that most of my evidence was really about understanding user motivation, settled on Empathize, then came back to Ideate with sharper reasoning tied to how much the team iterated on and discarded features. | E15: I kept blurring the line between adjacent stages. In my Step 2 table I put the "How might we" question under Define's output when it's really the bridge into Ideate, and called Ideate's output "a shortlist" when Ideate is supposed to be quantity-over-quality with no narrowing yet. I made almost the same mistake picking Instagram's most-invested stage — most of my "Ideate" evidence was actually describing understanding user motivation (Empathize/Define) or execution polish (Prototype/Test). | F15: When you're looking at a shipped product from the outside, is there a reliable way to tell which of two adjacent stages (like Define vs. Ideate) a team actually invested most in, given how easily their boundaries blur once all you can see is the finished result? | G15: For the Step 5 "why would I skip Define" question, I first wrote a reason to worry about skipping Define (tests later revealing new insights) instead of my own actual instinct for doing it. Next time I'd check whether I'm describing a cause of my own behavior or a consequence of the mistake before writing the answer down. | H15: This week's real shift was learning to catch myself substituting taste for principle, and to actually name why once I do — a distinction that started as a vague discomfort and turned into a mechanism I could point to by the end of the week, like checking whether a heuristic's real definition matches what I'm citing it for. Alongside that, choosing fidelity by naming the riskiest unproven assumption stopped being a framework I could recite and became something I actually leaned on — it's what let me block a task honestly instead of faking a shortcut around it. The clearest new idea was learning to ask whether I'd organised something by my own internal logic or by how the person actually using it thinks — a question I only learned to ask once, near the end of the week, and immediately wished I'd been asking all along. The pattern I keep noticing in myself is that I catch a loose thread, name it honestly, and then move on without closing it, rather than resolving it on the spot. Next week I want to run that internal-logic-vs-user-logic check on my own drafts before anyone else has to point it out, and rely less on two or three rounds of critique to catch what one honest self-check could have caught the first time.
A16: 46279 | B16: 2 | C16: 2.1 | D16: Journal (Task 2.1, Step 5) — Which stage do you think you'll personally be tempted to skip, and why? Define. Not simply from time pressure, but from the illusion of having already defined the problem clearly when I haven't actually brainstormed the problem statement enough — I might not even notice I've skipped it.
A17: 46280 | B17: 2 | C17: 2.4 | D17: Journal (Task 2.4, Step 5) — Which came from you, which from Claude, and which came from combining the two? From me: all eight Crazy Eights sketches, but five of them (nutrition, outing schedule, sleep schedule, bathing, activity tracker) clustered into "Routine & Care Consistency," which I recognized as off-target for this HMW and didn't carry forward — only my video-facetime sketch survived into a final direction. From Claude: all three of my final chosen directions are populated almost entirely by Claude's 25 divergent ideas — "Caregiver Vetting & Matching" and "Gradual Trust-Building Protocols" are entirely Claude-originated, and "Recreate the Owner's Presence" is five-sixths Claude ideas plus my one sketch. From combining the two: the real value was in selection, not generation — I initially picked "Monitoring & Safety Net" as my third direction, but Claude pointed out that theme's own stated logic ("reduces the owner's risk, doesn't build trust directly") didn't actually answer the HMW question, so I swapped it for "Gradual Trust-Building Protocols" instead — a better fit neither of us would have landed on alone.
A18: 46281 | B18: 2 | C18: 2.6 | D18: Completed Task 2.6 — read the NN/g usability-testing resources, wrote a five-task usability test script for PawPal's general booking flow (heading out of town, messaging a sitter, budget-constrained search, switching to sitter-side availability, booking + payment), revised it through several rounds after catching invented features (a "package" system and a reviews/track-record signal that weren't confirmed in Brief A), vague completion criteria, and a UPI-vs-credit-card mismatch, then had Claude review the final script. Built a five-screen HTML wireframe (browse/search, sitter profile, messaging, booking/payment, sitter-side application) and got it critiqued, which surfaced a disconnected navigation bar, missing trust/ratings signals, and an over-specified edge-case screen. Wrote up three things that worked, three that broke, and one surprise from that build process. | E18: I treated 'build the wireframe and get it critiqued' as satisfying 'run the test on one colleague,' but those are two different exercises — one is a design critique of the artefact, the other is watching a real person attempt the five tasks and observing where they stumble. I didn't catch that distinction until it was pointed out to me, and by then I'd already written a reflection answering a different question than Step 5 actually asked. | F18: When the wireframe was reviewed only against my own literal element list, the review never surfaced the trust/ratings signal I already knew mattered from the very first PawPal brief — how do I get a review to catch a known gap I forgot to ask about, rather than just checking my work against my own blind spots? | G18: I'd have checked the finished wireframe screen-by-screen against my own five test tasks before treating it as done — that would have caught that Screen 5 has no actual day/time availability element at all, which meant Task 4 couldn't even be attempted on the prototype as built.
A19: 46281 | B19: 2 | C19: 2.7 | D19: What I learned — Module 2, running the whole loop on PawPal. Where the process helped: The five-stage structure caught mistakes I wouldn't have caught working freeform. In Empathize, my first pass at clustering my own interview notes dropped the two richest insights entirely (that the family never found a boarding option they trusted, and that the dog only walked with the hired sitter when I was nearby) -- the discipline of one observation per line, then group, is what surfaced that gap, not instinct. In Define, my first two POV drafts both named a solution ("dog walker," "an entity," "automated technology") instead of staying at the level of the actual need, and the second one claimed a "days/months" timeframe the research never supported -- the POV format's rigidity is what made those errors visible enough to fix before they became load-bearing. The pressure-test step caught two more real problems in my five HMW questions -- one baked in a strategy ("gradually reduce"), one was too generic to be anchored to my actual research -- and both would have quietly warped whatever I designed downstream if I hadn't run that specific check. Ideate is where the process helped the most, and in the way I expected least. Left alone, five of my eight Crazy Eights sketches drifted into a different, more comfortable problem ("what should a pet-care app include") rather than the actual HMW I was supposed to answer. Claude's 25 divergent ideas gave me directions I genuinely wouldn't have generated myself, and the real value showed up at selection, not generation: I picked "Monitoring & Safety Net" as a final direction because it sounded solid, and only caught that its own stated logic didn't answer the actual question when it was checked against the HMW itself, not against my gut feeling. Prototype and Test are where the loop proved itself hardest, because they're the two stages I'm least naturally rigorous about. The fidelity framework -- name the riskiest unproven assumption, then pick the cheapest thing that actually tests it -- stopped me from jumping straight to a wireframe for equipment layout and straight to hi-fi for a matching concept that wasn't validated yet. And the usability test genuinely delivered: a real colleague got stuck on Task 4 because the sitter-availability screen has no day/time element at all -- a concrete failure I hadn't caught in two separate reviews of my own wireframe. Where it felt like overhead: Some of the sequence felt like re-proving something I already half-knew. The core "trust isn't transferred by vetting and payment alone" insight was visible from the very first interview, and I re-derived versions of it through clustering, the POV statement, and the HMW set -- useful for precision, but by the third pass it felt more like reformatting the same insight than discovering anything new. The literal-instruction wireframe build is where the overhead was most costly, and it was self-inflicted: because I built to a strict "only what's on the list" constraint, ratings and reviews -- the brief's number one stated concern -- never made it onto any screen, even though I'd known about that concern since Task 2.2. That wasn't the process failing; it was me treating literal compliance as a substitute for judgment. And deciding fidelity for all three ideation directions, one at a time, with a full "riskiest assumption" writeup for each, was arguably more deliberation than two of those decisions (both landed on paper sketch) actually needed -- at that fidelity level the whole point is that the decision should be cheap and fast, and the analysis around it started to cost more than the sketch itself would have.
A20: 46282 | B20: 3 | C20: 3.2 | D20: Completed Task 3.2 — picked ten real screens (five liked, five disliked) across Splitwise, Rapido, the default Calculator, Google Classroom, Amazon Alexa, YouTube Music, Settings, an Alarm app, Zomato, and Savana. Wrote a structured six-field critique for each (user's goal, hierarchy, type, colour, spacing, heuristics violated/respected), then went back through all ten specifically checking whether each named heuristic was actually being used correctly. Found two clear cases where I'd dressed up a personal preference as a heuristic violation — citing "User control and freedom" to justify wanting a dark-mode toggle on the Calculator, and redefining "functional" broadly enough that the Savana palette's brand-feeling effect could count as a usability principle rather than an aesthetic one. | E20: I initially accepted both of those two citations as legitimate when I first wrote them — it was only when I went back and checked the heuristic's actual textbook definition against what I'd written that the gap between "this sounds like an official reason" and "this is actually what the heuristic means" became visible. In the moment of writing the critique, both felt like principled observations, not disguised taste. | F20: Is there a check I can run per critique line, in the moment of writing it, that would catch this stretch before I write it down — something like asking "would I still call this a violation if I described the problem without naming any heuristic at all" — rather than only catching it on a second pass afterward? | G20: I'd check each heuristic's original definition before writing the justifying sentence, instead of writing the observation I wanted to make first and then reaching for whichever of the ten heuristics sounded closest to it.
A21: 46282 | B21: 3 | C21: 3.3 | D21: Completed Task 3.3 — spent time in Material 3's foundations, styles, and components, then skimmed the Apple Human Interface Guidelines foundations (Accessibility, Layout, Color, Typography, Materials, Motion, SF Symbols) to see where a second system makes different choices for the same problems. Compared how each documents the Button component: Material specs a full variant-by-state grid, while Apple frames button design as a set of decisions and only rigorously enumerates states where feedback is genuinely non-obvious (visionOS). Wrote three sentences on what a design system buys a team and what departing from one costs, revising twice until the answer used that same spec-everything-vs-spec-only-exceptions mechanism to explain both halves symmetrically. Asked Claude the literal Step 5 question on what a designer is protecting by calling something off-pattern, and when it's reasonable to push back. | E21: I first tried to force Apple's Buttons page into the same variant-times-state grid Material uses, before recognizing that doing so would be inventing structure that isn't actually in Apple's documentation — the two systems aren't organized on the same premise at all, one is a catalog to select from and the other is a set of context-dependent decisions. | F21: In practice, when a designer actually tells me a request is off-pattern, how do I tell quickly which of the things it could be protecting — the token system, cross-screen consistency, or an already-settled decision — since those call for pretty different responses from me and I don't yet have real experience telling them apart in the moment. | G21: I'd write the underlying "why do these systems actually differ" reasoning before writing the surface-level "what does a system buy you" answer, instead of writing the generic version first and only sharpening it into something evidence-based after being pushed to fold in what I'd already found in Step 3.
A22: 46283 | B22: 4 | C22: 4.1 | D22: Completed Task 4.1 — read the wireframing fundamentals resources, then wrote seven working definitions (structure, hierarchy, content priority, key interactions, plus what a wireframe must exclude: final colour, real imagery, polished type) after a first pass that just restated the given must-include/must-exclude labels rather than defining them. Took three real screens from my reference library (Zomato home, an Alarm app, Splitwise's Activity page) and wireframed each backwards — reducing the finished screen to its structural skeleton — then asked Claude to critique whether any of the three reductions still carried a visual decision dressed up as a structural one. Added all three reduced wireframes to my board next to the screens they came from. | E22: My first attempt at Step 2 just repeated the vocabulary the task already gave me ("structure means the sections on a screen") instead of actually defining what each term means in practice — I didn't see the difference until it was pointed out that I'd been given the labels, not asked to restate them. | F22: When Claude's critique flags one of my three reduced wireframes as still carrying a visual decision, what's the fastest way to tell whether that's a genuine structural-vs-visual conflation on my part, or just a case where the structural choice and the visual choice happen to look the same on that particular screen? | G22: I'd have picked one screen with heavy colour-dependent hierarchy (like the Alarm app's on/off toggle) and one with none, before starting, instead of picking three screens that happened to be structurally similar — a more varied set would have stress-tested the should-contain/must-not-contain distinction harder.
A23: 46283 | B23: 4 | C23: 4.2 | D23: Started Task 4.2 (Practise: Sketching by hand). Read the paper-prototyping article and located printable browser-frame templates for Step 1. Step 2 asks for eight timed sketches of a claims list/filter/detail screen on paper — I don't have a physical drawing pad or printer set up right now, so I marked Step 2 onward Blocked rather than skip past it or fake it digitally, since the whole point of paper is the speed and disposability a mouse-drawn version wouldn't give me. | E23: Nothing about the task content confused me — the block is purely material (no drawing pad on hand), not conceptual. | F23: Once I do get a drawing pad, is there a meaningful difference between sketching on paper and sketching on a tablet with a stylus for this specific exercise, or does the paper-specific speed/disposability argument hold just as well on a tablet? | G23: I'd keep a basic sketchpad in reach for exactly this kind of task from the start of the module, since I could tell from Step 1's reading that hand-sketching was coming and didn't prepare for it.
A24: 46283 | B24: 4 | C24: 4.3 | D24: Completed Task 4.3 — read the IA and user-flow resources, then built a 42-item (later 41, after removing one item that didn't belong) content/function inventory for Harvest Hub covering orders, inventory, deliveries, and the owner's business-summary view. Grouped the inventory into a sitemap organised by role (Ops, Warehouse, Owner) rather than by feature area, revised it through three rounds after critique caught a missing order-creation path, an undefined driver-facing access question, and a redundant read-only inventory node I ended up removing entirely rather than relocating. Drew the order-to-delivery user flow as the single most important task, covering four decision points (stock availability, driver availability, order edited after dispatch, delivered on time) and revised it once more to replace two dead-end escalation boxes with concrete outcomes (cancel/hold-with-timer, reassign/hold-with-timer) and add a re-verify step for the edited-after-dispatch loop. Asked Claude the literal Step 5 question and got back three real gaps (order creation, the owner's data source, and inventory-update triggers not shown) and two internal-logic issues (driver workload buried a screen away from the reassign decision; late-marking happening automatically instead of surfacing a reason first). | E24: On the second sitemap round I got stuck on where a read-only inventory-browse screen should live under Ops, until I just removed it entirely on the third round rather than relocating it — Claude pointed out afterwards that this was actually the better fix, since "stock check" was already covered inside Order Detail. I hadn't consciously reasoned toward that; I think I cut it because the sitemap felt cluttered, not because I'd identified the redundancy. | F24: For the two escalation paths I resolved with "Hold (timer)", I still don't have an answer for what happens when the timer runs out — does that count as a genuinely separate error path I still need to design, or is "ops checks it manually" an acceptable stopping point for a flow at this fidelity? | G24: I'd have asked myself the Step 5 question ("what's internal logic vs. user logic") before finishing the flow, not after — the driver-workload placement issue was baked into the sitemap two steps back in Task 4.3 Step 3, and I could have caught it there instead of carrying it into the flow.
A25: 46284 | B25: 4 | C25: 4.4 | D25: Started Task 4.4 (Dashboards and internal tools) — watched the guide and read the NN/g dashboard-design article for Step 1. | E25: Nothing confusing yet — this was a straightforward watch-and-read step. | F25: How much of what I'm about to learn about dashboard anatomy will actually transfer cleanly to Harvest Hub, versus needing rethinking once I see the real ops/warehouse/owner screens side by side? | G25: Nothing to do differently on a single reading step — too early to tell.
A26: 46285 | B26: 4 | C26: 4.2 | D26: Got a way to sketch by hand and finished Task 4.2 (Sketching by hand), which had been genuinely Blocked since the 18th. Ran the eight-minute/eight-sketch timed exercise twice (a claims list with filters and a detail panel, then a settings page), picked my best from each set, redrew them larger, and annotated the reasoning behind specific choices — marking the selected claims row with a border plus shading instead of colour alone so it survives greyscale scanning, and separating Log out from routine settings so it can't be tapped by accident. Photographed everything into `02-Module-Work`. | E26: Nothing about the sketching itself was confusing — the only open question my own annotations left behind was what the claims screen's detail panel shows before any row is selected, and whether the settings screen's Log out grouping is a real third section or just sitting alone. | F26: Those two questions from my own annotations — the claims detail panel's empty state, and whether "Support" is a real group — are still open. Do they need answering now, or are they the kind of thing that gets resolved naturally once I actually build the screen? | G26: I'd have answered those two questions in the annotation itself instead of leaving them as unresolved hedges ("Support-ish") — same pattern I noticed in this week's review: naming a loose thread honestly, then moving on without closing it.
A27: 46286 | B27: 4 | C27: 4.4 | D27: Finished Task 4.4. Wrote the dashboard anatomy definitions (navigation, filters, KPIs, primary data view, detail panel, actions), revising twice after feedback — tightening Detail panel from "a feature" to "a selected record in the primary data view," and swapping generic consumer-app KPI examples (retention, MAU, AOV) for ones that actually belong on Harvest Hub (late order rate, low-stock items, unassigned orders). Listed the six problems dense interfaces face, then built a doc (`Dense-Interface-Analysis.docx`, saved to `05-Reference-Library`) cross-checking all six against five real reference screens, noting honestly where a problem didn't apply rather than inventing a solution for it. Asked Claude the literal Step 5 question on what consumer-app teams get wrong specifying enterprise dashboards, then checked its five points against my own six-problem list — found one real gap (treating "clean/simple" as the goal, when dense interfaces actually need "fast to parse") that my list didn't cover in either direction. | E27: My reference library turned out to be entirely mobile/touch screens, so "keyboard use" scored "No" on all five — not because the problem doesn't matter, but because nothing in my existing references could show me a real solution for it, even though it's arguably the most relevant of the six for Harvest Hub specifically, since ops runs it on laptops. | F27: I flagged that the new "clean vs. fast-to-parse" point is actually a root cause sitting above two of my six problems (scanning, data density) rather than a coequal seventh item — is that distinction worth restructuring a checklist around in general, or is a flat list always good enough in practice once you know the hierarchy is there? | G27: I'd add at least one desktop, keyboard-driven reference screen to my library now rather than leaving keyboard use as a diagnosed-but-unsolved gap — it's the one problem on my list with zero real example behind it, and it's the one most likely to matter for the actual product I'm building requirements for.
A28: 46287 | B28: 4 | C28: 4.5 | D28: Worked through the HTML tutorial through forms and the CSS box-model tutorial (Flexbox Froggy still in progress), learned what semantic HTML means and why a <button> isn't a styled <div>, then did the real exercise: opened the Task 4.6 Settings prototype's actual source code and read it end to end — mapped its structure, found it uses only one real design-system component (the log-out icon) while everything else is hardcoded hex, and found a genuine bug just from reading renderVals(): both buttons in the log-out confirmation panel call the same cancelLogout handler, so the confirm action never actually fires. Then asked Claude which CSS/layout changes are cheap vs. expensive against that real code, and wrote down the five answers that surprised me — duplicated row-gradient blocks being "cheap but tedious," the confirm-panel bug looking like a one-line fix but having no real sign-out logic behind it, converting the panel to a real modal, the hand-built-toggle-vs-system-component tradeoff, and collapsing five duplicated style blocks into one shared token. | E28: Honestly, Step 2 (Flexbox Froggy) is still marked In progress, not Done — I moved on to Step 3 before finishing it, and by the time I was deep in reading real code for Step 4, it stayed unfinished. | F28: Now that I've actually found a real bug by reading code instead of just clicking around a prototype, is code-reading meant to become a standing habit before treating any Claude Design prototype as finished, or is it specific to states/interactions like this Log-out flow? | G28: I'd have gone back and finished Flexbox Froggy before starting Step 3, instead of leaving it half-done and moving forward — same avoidance pattern I've caught myself in before (naming a loose thread, then moving on without closing it).
A29: 46287 | B29: 4 | C29: 4.6 | D29: Built the Settings screen prototype in Claude Design from a detailed prompt — but first checked the Task 4.2 wireframe against my own Task 4.2 journal annotation and found the wireframe never actually isolated Log out the way I'd said it should be, so I wrote the prompt to fix that instead of reproducing the gap. Ran it through 10 real rounds of inline-canvas-comment edits (logged in the project's own CHANGELOG.md), then wrote up the round log with an honest read of what actually happened to the Log-out safety requirement across those 10 rounds: it started differentiated three separate ways (spacing, a divider, distinct color/border), and by round 10 two of those three were gone — not because any single round targeted Log out, but because two separately reasonable fixes (a text-wrap fix in round 7, a gradient-consistency fix in round 10) combined to erode it without either round meaning to. Rewrote my original one-time prompt instruction into a standing prompting technique — check every future round against the core requirement, flag any tradeoff, and state at the end of the round whether it still holds — and added it to both prompt libraries. | E29: Catching the erosion only after all 10 rounds were done — at the time, each individual round felt like a reasonable, isolated fix, and I couldn't have flagged round 7 or round 10 as "the problem" while I was inside them. | F29: Would running my new "protect the core requirement" check after every single round (rather than doing 10 rounds and then auditing) have actually caught this in real time, or does checking too early risk stalling genuinely unrelated fixes? | G29: I'd have written the "protect the core requirement" version of the prompt before round 1, not after round 10 — the erosion only happened because nothing carried the requirement forward past the first prompt.
A30: 46287 | B30: 4 | C30: 4.7 | D30: Read both NN/g articles on states and edge cases, then listed all eleven states a data-heavy screen can be in (first-use empty, user-cleared empty, loading, partial load, error, no results after filtering, permission denied, offline, too much data, one item, one thousand items). Took the Task 4.6 Settings prototype into Claude Design and built out eight of those eleven as real screens (more than the six required) — Loading, Partial Load, Error, Offline, Permission Denied, One Item, One Thousand Items, No Results After Filtering. Wrote real copy for each rather than leaving placeholder text, then reviewed all eight against the rule that error-type messages must say both what happened and what to do next — found four states that fully pair the two (Partial Load's Retry, Error's Try Again, Permission Denied's Contact Your Admin, No Results' Clear Search plus suggestions), and two genuine gaps where the copy names the problem but gives no actionable next step: the Offline banner and the One Item locked-plan message. | E30: This is the first task where I had to decode another Claude Design "Bundled Page" export that was a multi-artboard board rather than a single interactive component — took a moment to recognize the eight boards were static side-by-side artboards sharing one showNotes toggle, not eight instances of one stateful component. | F30: For the two gaps I found (Offline, One Item), is the fix always "add a button," or is there a real case for leaving a state passive — like Offline, where the system might just reconnect on its own without needing the user to do anything? | G30: I'd have checked each state's copy against the "what happened + what to do next" rule as I wrote it, rather than writing all eight boards first and auditing afterward — I'd have caught the two gaps while still in Claude Design, where fixing them costs one round instead of a separate write-up.
A31: 46287 | B31: 4 | C31: 4.8 | D31: Finished Task 4.8. Identified order-to-delivery as the single most important Harvest Hub flow, had Claude walk me through the whole flow like I knew nothing about Harvest Hub, then wireframed the Order Management screen by hand (a table of orders plus a detail panel with Stock Check and Assign Driver, and a Resolve Stock Shortfall modal). Self-reviewed it against the five Task 3.1 checks — hierarchy, spacing, alignment, contrast, primary action — and passed spacing/alignment/contrast but flagged three real problems: the Resolve Shortfall button outweighed +New Order (the actual page-level primary action), one row (#10230) had an inconsistent extra kebab menu no other row had, and the Assign Driver panel header had leftover design-annotation copy ("WORKLOAD VISIBLE HERE") instead of real UI text. Fixed all three. | E31: Caught myself twice: once when what I'd built looked like a clean digital mockup rather than the paper wireframe the step actually asked for, and once when I said "looks like step 3 is already done" without having actually reviewed it myself — I'd marked steps 1-4 Done from memory, not from re-checking the work.
A32: 46288 | B32: 4 | C32: 4.9 | D32: Finished Task 4.9. Wrote out the seven design-time accessibility responsibilities (colour contrast, target size, focus order, focus visibility, not using colour alone, label clarity, text alternatives) and audited the Task 4.8 Order Management wireframe against every one — one clean pass (colour-alone, since late orders already carry both a coloured border and literal "LATE" text) and five flagged (contrast on the red LATE tag and stock-check text, target size on the small kebab/bell/account icons, focus order across the two-column panel and modal, no focus-visible treatment specified anywhere, and several icon-only controls with no accessible name written down). Wrote the Claude Design prompt naming the wireframe attachment, then rebuilt the whole screen in Claude Design with all five accessibility fixes plus the three Task 4.8 self-review fixes folded in. | E32: Wanted to actually trust the rebuild rather than just eyeball it, so I read the generated code directly instead of relying on how it looked — grepped for the focus-visible outline, the dialog/inert/focus-restore pattern, and the per-row aria-labels, and only then was I confident all eight fixes (five accessibility, three self-review) were genuinely there and not just visually implied.
A33: 46288 | B33: 4 | C33: 4.10 | D33: Finished Task 4.10. Picked PawPal's Sitter Verification Queue — an internal admin screen the brief itself left undefined ("maybe some kind of verification") and the natural other half of the sitter-application screen from Task 2.6. Wrote a ten-line description and generated it cold; found one real gap — no bulk action anywhere, even though Task 4.10's own Step 1 wording had named "a bulk action" as a requirement, which then never made it into the actual ten lines I wrote. Rewrote the description twice more, keeping all three screens: rewrite 1 named the bulk-selection mechanism explicitly and the gap closed completely (plus an unprompted, considerate touch — it tells you which selected users get skipped from a bulk action and why); rewrite 2 resolved one remaining tension between two of my own points (checkbox-first vs. verification-status-leftmost), and the rebuild changed exactly that one thing and nothing else. | E33: Misread "do this three times" at first — thought it meant three brand-new rewrites on top of the original, and was ready to write a fourth screen, until I checked with Claude and settled that the original cold build counts as the first of the three.
A34: 46288 | B34: 5 | C34: 5.1 | D34: Finished Task 5.1 (The basics of good project management). Watched the video and took notes, drew the iron triangle with one sentence per side on what changing scope, time, or cost forces to give elsewhere, defined milestone/dependency/critical path/stakeholder/risk register in my own words (revised critical path after realizing I had it backwards — it's not the fastest path, it's the longest chain of dependent tasks that sets the minimum project duration), then asked Claude the literal Step 4 question on how each concept actually shows up in day-to-day PM work rather than just what it means. Noted Dependency as the concept I expect to matter most in my first project — tracking what work is actually waiting on what, and chasing the upstream blocker before it quietly turns a status from green to red. | E34: Caught my own critical path definition being backwards before it went in the tracker — I had it as "the path that finishes fastest," when it's actually the longest chain of dependent tasks, the one with zero slack that sets the whole project's minimum duration.

Sheet Phase 2 Readiness
A1: Area | B1: I can… | C1: Rating 1-5 | D1: Comments
A2: Working with Claude | B2: I can write a structured prompt that gets usable output first time
A3: Working with Claude | B3: I can diagnose why a prompt failed and change one thing at a time
A4: Working with Claude | B4: I know which claims to verify and I actually verify them
A5: Working with Claude | B5: I can delegate a multi-step task to Cowork and judge the result critically
A6: Working with Claude | B6: I can write and refine a Skill that triggers when it should
A7: Design partnership | B7: I can look at a screen and say specifically why it is or is not working
A8: Design partnership | B8: I can give a designer feedback they can act on, without designing it myself
A9: Design partnership | B9: I can tell the difference between my taste and an established principle
A10: Design partnership | B10: I know what a design system buys a team and what departing from one costs
A11: Specification and prototyping | B11: I can go from a flow to a clickable prototype in Claude Design
A12: Specification and prototyping | B12: I can describe a screen precisely enough that the first build comes back close to what I meant
A13: Specification and prototyping | B13: I can read HTML and CSS well enough to know which requests are expensive
... A30: Working here | B30: I can present to a client with confidence in the reasoning behind my work
